Workbook

Sheet RAW_INPUT
A1: TNDS Sales Data Template — RAW INPUT (QuickBooks Export)
A2: Drop QuickBooks export here. Required: Date, Qty, Sales Price OR Total Sales. Extra columns are ignored by the pipeline.
A3: Date | B3: Customer | C3: Invoice # | D3: Item / Description | E3: Qty | F3: Sales Price | G3: Total Sales | H3: Tax | I3: Notes
A4: REQUIRED — MM/DD/YYYY | B4: Optional — for reference | C4: Optional — for reference | D4: Optional | E4: REQUIRED if no Total Sales | F4: REQUIRED if no Total Sales | G4: Pipeline uses this (or computes Qty×Price) | H4: Optional | I4: Optional
A5: 45600 | B5: Acme Petroleum | C5: INV-1001 | D5: Diesel Delivery | E5: 420 | F5: 3.91 | G5: =IF(OR(E5="",F5=""),"",E5*F5) -> 1642.2 | H5: 47.62
A6: 45601 | B6: Front Range Inc | C6: INV-1002 | D6: Unleaded Delivery | E6: 380 | F6: 3.91 | G6: =IF(OR(E6="",F6=""),"",E6*F6) -> 1485.8 | H6: 0
A7: 45602 | B7: Arkansas Valley Oil | C7: INV-1003 | D7: Diesel Delivery | E7: 510 | F7: 3.88 | G7: =IF(OR(E7="",F7=""),"",E7*F7) -> 1978.8 | H7: 57.39
A8: 45603 | B8: Summit Logistics | C8: INV-1004 | D8: Fleet Fuel Drop | E8: 465 | F8: 3.88 | G8: =IF(OR(E8="",F8=""),"",E8*F8) -> 1804.2 | H8: 52.32
A9: 45604 | B9: Acme Petroleum | C9: INV-1005 | D9: Diesel Delivery | E9: 490 | F9: 3.85 | G9: =IF(OR(E9="",F9=""),"",E9*F9) -> 1886.5 | H9: 0
A10: 45607 | B10: Springs Delivery Co | C10: INV-1006 | D10: Unleaded Delivery | E10: 440 | F10: 3.85 | G10: =IF(OR(E10="",F10=""),"",E10*F10) -> 1694 | H10: 49.13
A11: 45608 | B11: Front Range Inc | C11: INV-1007 | D11: Fleet Fuel Drop | E11: 520 | F11: 3.82 | G11: =IF(OR(E11="",F11=""),"",E11*F11) -> 1986.4 | H11: 57.61
A12: 45609 | B12: Western Slope Transport | C12: INV-1008 | D12: Fleet Fuel Drop | E12: 478 | F12: 3.82 | G12: =IF(OR(E12="",F12=""),"",E12*F12) -> 1825.96 | H12: 0
A13: 45610 | B13: Pikes Peak Energy | C13: INV-1009 | D13: Fleet Fuel Drop | E13: 502 | F13: 3.8 | G13: =IF(OR(E13="",F13=""),"",E13*F13) -> 1907.6 | H13: 55.32
A14: 45611 | B14: Centennial Hauling | C14: INV-1010 | D14: Diesel Delivery | E14: 461 | F14: 3.8 | G14: =IF(OR(E14="",F14=""),"",E14*F14) -> 1751.8 | H14: 50.8
A15: 45614 | B15: Mountain View Fleet | C15: INV-1011 | D15: Line Flush Service | E15: 1 | F15: 1250 | G15: =IF(OR(E15="",F15=""),"",E15*F15) -> 1250 | H15: 0
A16: 45615 | B16: Centennial Hauling | C16: INV-1012 | D16: Unleaded Delivery | E16: 435 | F16: 3.79 | G16: =IF(OR(E16="",F16=""),"",E16*F16) -> 1648.65 | H16: 47.81
... A445: 46224 | B445: Colorado Fuel Corp | C445: INV-1441 | D445: Synthetic Blend Package | E445: 160 | F445: 45.38 | G445: =IF(OR(E445="",F445=""),"",E445*F445) -> 7260.8 | H445: 210.56

Sheet PIPELINE_READY
A1: PIPELINE_READY — Drop this CSV into data/raw/ after exporting
A2: Minimum viable format. config.py reads: DATE_COLUMN='Date', QTY_COLUMN='Qty', PRICE_COLUMN='Sales Price' OR TARGET_COLUMN='Total Sales'
A3: Date | B3: Qty | C3: Sales Price
A4: =IF(RAW_INPUT!A5="","",RAW_INPUT!A5) -> 45600 | B4: =IF(RAW_INPUT!A5="","",RAW_INPUT!E5) -> 420 | C4: =IF(RAW_INPUT!A5="","",RAW_INPUT!F5) -> 3.91
A5: =IF(RAW_INPUT!A6="","",RAW_INPUT!A6) -> 45601 | B5: =IF(RAW_INPUT!A6="","",RAW_INPUT!E6) -> 380 | C5: =IF(RAW_INPUT!A6="","",RAW_INPUT!F6) -> 3.91
A6: =IF(RAW_INPUT!A7="","",RAW_INPUT!A7) -> 45602 | B6: =IF(RAW_INPUT!A7="","",RAW_INPUT!E7) -> 510 | C6: =IF(RAW_INPUT!A7="","",RAW_INPUT!F7) -> 3.88
A7: =IF(RAW_INPUT!A8="","",RAW_INPUT!A8) -> 45603 | B7: =IF(RAW_INPUT!A8="","",RAW_INPUT!E8) -> 465 | C7: =IF(RAW_INPUT!A8="","",RAW_INPUT!F8) -> 3.88
A8: =IF(RAW_INPUT!A9="","",RAW_INPUT!A9) -> 45604 | B8: =IF(RAW_INPUT!A9="","",RAW_INPUT!E9) -> 490 | C8: =IF(RAW_INPUT!A9="","",RAW_INPUT!F9) -> 3.85
A9: =IF(RAW_INPUT!A10="","",RAW_INPUT!A10) -> 45607 | B9: =IF(RAW_INPUT!A10="","",RAW_INPUT!E10) -> 440 | C9: =IF(RAW_INPUT!A10="","",RAW_INPUT!F10) -> 3.85
A10: =IF(RAW_INPUT!A11="","",RAW_INPUT!A11) -> 45608 | B10: =IF(RAW_INPUT!A11="","",RAW_INPUT!E11) -> 520 | C10: =IF(RAW_INPUT!A11="","",RAW_INPUT!F11) -> 3.82
A11: =IF(RAW_INPUT!A12="","",RAW_INPUT!A12) -> 45609 | B11: =IF(RAW_INPUT!A12="","",RAW_INPUT!E12) -> 478 | C11: =IF(RAW_INPUT!A12="","",RAW_INPUT!F12) -> 3.82
A12: =IF(RAW_INPUT!A13="","",RAW_INPUT!A13) -> 45610 | B12: =IF(RAW_INPUT!A13="","",RAW_INPUT!E13) -> 502 | C12: =IF(RAW_INPUT!A13="","",RAW_INPUT!F13) -> 3.8
A13: =IF(RAW_INPUT!A14="","",RAW_INPUT!A14) -> 45611 | B13: =IF(RAW_INPUT!A14="","",RAW_INPUT!E14) -> 461 | C13: =IF(RAW_INPUT!A14="","",RAW_INPUT!F14) -> 3.8
A14: =IF(RAW_INPUT!A15="","",RAW_INPUT!A15) -> 45614 | B14: =IF(RAW_INPUT!A15="","",RAW_INPUT!E15) -> 1 | C14: =IF(RAW_INPUT!A15="","",RAW_INPUT!F15) -> 1250
A15: =IF(RAW_INPUT!A16="","",RAW_INPUT!A16) -> 45615 | B15: =IF(RAW_INPUT!A16="","",RAW_INPUT!E16) -> 435 | C15: =IF(RAW_INPUT!A16="","",RAW_INPUT!F16) -> 3.79
... A2003: =IF(RAW_INPUT!A2004="","",RAW_INPUT!A2004) | B2003: =IF(RAW_INPUT!A2004="","",RAW_INPUT!E2004) | C2003: =IF(RAW_INPUT!A2004="","",RAW_INPUT!F2004)

Sheet QB_COLUMN_MAP
A1: QuickBooks Export Column Mapping Reference
A2: QuickBooks Column Name | B2: Template Column | C2: Required? | D2: Notes
A3: Date | B3: Date | C3: YES | D3: Transaction date. Rename if QB exports as 'Txn Date'
A4: Qty | B4: Qty | C4: If no Total | D4: Units. May be 'Quantity' in some QB reports
A5: Sales Price | B5: Sales Price | C5: If no Total | D5: Unit price. May be 'Rate' in QB
A6: Amount | B6: Total Sales | C6: If no Qty/Price | D6: Pre-computed total. Rename to 'Total Sales'
A7: Customer | B7: Customer | C7: No | D7: Kept for reference, not used by pipeline
A8: Invoice No. | B8: Invoice # | C8: No | D8: Reference only
A9: Item Description | B9: Item / Description | C9: No | D9: Reference only
A10: Tax | B10: Tax | C10: No | D10: Not used by pipeline currently
A11: Memo | B11: Notes | C11: No | D11: Optional context

Sheet Analysis
A1: TNDS SALES DATA — COMPREHENSIVE ANALYSIS
A2: Source: RAW_INPUT sheet | All figures in USD unless noted
A4: KEY METRICS SUMMARY
A6: Total Revenue | B6: =SUM(RAW_INPUT!G5:G445) -> 790660.08 | D6: Avg Sale Size | E6: =B6/B7 -> 1792.88 | G6: Date Range Start | H6: =MIN(RAW_INPUT!A5:A445) -> 45600
A7: Total Transactions | B7: =COUNTA(RAW_INPUT!A5:A445) -> 441 | D7: Avg Fuel Price/Gal | E7: {=SUMPRODUCT((RAW_INPUT!F5:F445<20)*(RAW_INPUT!G5:G445))/SUMPRODUCT((RAW_INPUT!F5:F445<20)*(RAW_INPUT!E5:E445))} -> 3.6986725 | G7: Date Range End | H7: =MAX(RAW_INPUT!A5:A445) -> 46224
A8: Total Fuel Gallons | B8: {=SUMPRODUCT((RAW_INPUT!F5:F445<20)*(RAW_INPUT!E5:E445))} -> 181158 | D8: Service Transactions | E8: {=SUMPRODUCT((RAW_INPUT!E5:E445=1)*(RAW_INPUT!F5:F445>=20)*1)} -> 72 | G8: Unique Customers | H8: {=SUMPRODUCT(1/COUNTIF(RAW_INPUT!B5:B445,RAW_INPUT!B5:B445))} -> 15
A10: MONTHLY REVENUE TREND
A11: Month | B11: Revenue | C11: # Transactions | D11: Fuel Gallons | E11: Avg Price/Gal | F11: Avg Sale Size
A12: =DATE(YEAR(MIN(RAW_INPUT!A5:A445)),MONTH(MIN(RAW_INPUT!A5:A445)),1) -> 45597 | B12: {=SUMPRODUCT((RAW_INPUT!A5:A445>=A12)*(RAW_INPUT!A5:A445<A13)*RAW_INPUT!G5:G445)} -> 30502.09 | C12: {=SUMPRODUCT((RAW_INPUT!A5:A445>=A12)*(RAW_INPUT!A5:A445<A13)*1)} -> 18 | D12: {=SUMPRODUCT((RAW_INPUT!A5:A445>=A12)*(RAW_INPUT!A5:A445<A13)*(RAW_INPUT!F5:F445<20)*RAW_INPUT!E5:E445)} -> 7660 | E12: {=IFERROR(SUMPRODUCT((RAW_INPUT!A5:A445>=A12)*(RAW_INPUT!A5:A445<A13)*(RAW_INPUT!F5:F445<20)*RAW_INPUT!G5:G445)/D12,0)} -> 3.8188107 | F12: =IFERROR(B12/C12,0) -> 1694.5606
A13: =EDATE(A12,1) -> 45627 | B13: {=SUMPRODUCT((RAW_INPUT!A5:A445>=A13)*(RAW_INPUT!A5:A445<A14)*RAW_INPUT!G5:G445)} -> 28816.9 | C13: {=SUMPRODUCT((RAW_INPUT!A5:A445>=A13)*(RAW_INPUT!A5:A445<A14)*1)} -> 21 | D13: {=SUMPRODUCT((RAW_INPUT!A5:A445>=A13)*(RAW_INPUT!A5:A445<A14)*(RAW_INPUT!F5:F445<20)*RAW_INPUT!E5:E445)} -> 6999 | E13: {=IFERROR(SUMPRODUCT((RAW_INPUT!A5:A445>=A13)*(RAW_INPUT!A5:A445<A14)*(RAW_INPUT!F5:F445<20)*RAW_INPUT!G5:G445)/D13,0)} -> 3.6529361 | F13: =IFERROR(B13/C13,0) -> 1372.2333
A14: =EDATE(A12,2) -> 45658 | B14: {=SUMPRODUCT((RAW_INPUT!A5:A445>=A14)*(RAW_INPUT!A5:A445<A15)*RAW_INPUT!G5:G445)} -> 33836.2 | C14: {=SUMPRODUCT((RAW_INPUT!A5:A445>=A14)*(RAW_INPUT!A5:A445<A15)*1)} -> 21 | D14: {=SUMPRODUCT((RAW_INPUT!A5:A445>=A14)*(RAW_INPUT!A5:A445<A15)*(RAW_INPUT!F5:F445<20)*RAW_INPUT!E5:E445)} -> 8338 | E14: {=IFERROR(SUMPRODUCT((RAW_INPUT!A5:A445>=A14)*(RAW_INPUT!A5:A445<A15)*(RAW_INPUT!F5:F445<20)*RAW_INPUT!G5:G445)/D14,0)} -> 3.4524107 | F14: =IFERROR(B14/C14,0) -> 1611.2476
A15: =EDATE(A12,3) -> 45689 | B15: {=SUMPRODUCT((RAW_INPUT!A5:A445>=A15)*(RAW_INPUT!A5:A445<A16)*RAW_INPUT!G5:G445)} -> 37066.84 | C15: {=SUMPRODUCT((RAW_INPUT!A5:A445>=A15)*(RAW_INPUT!A5:A445<A16)*1)} -> 19 | D15: {=SUMPRODUCT((RAW_INPUT!A5:A445>=A15)*(RAW_INPUT!A5:A445<A16)*(RAW_INPUT!F5:F445<20)*RAW_INPUT!E5:E445)} -> 8310 | E15: {=IFERROR(SUMPRODUCT((RAW_INPUT!A5:A445>=A15)*(RAW_INPUT!A5:A445<A16)*(RAW_INPUT!F5:F445<20)*RAW_INPUT!G5:G445)/D15,0)} -> 3.8136992 | F15: =IFERROR(B15/C15,0) -> 1950.8863
A16: =EDATE(A12,4) -> 45717 | B16: {=SUMPRODUCT((RAW_INPUT!A5:A445>=A16)*(RAW_INPUT!A5:A445<A17)*RAW_INPUT!G5:G445)} -> 38946.24 | C16: {=SUMPRODUCT((RAW_INPUT!A5:A445>=A16)*(RAW_INPUT!A5:A445<A17)*1)} -> 21 | D16: {=SUMPRODUCT((RAW_INPUT!A5:A445>=A16)*(RAW_INPUT!A5:A445<A17)*(RAW_INPUT!F5:F445<20)*RAW_INPUT!E5:E445)} -> 9023 | E16: {=IFERROR(SUMPRODUCT((RAW_INPUT!A5:A445>=A16)*(RAW_INPUT!A5:A445<A17)*(RAW_INPUT!F5:F445<20)*RAW_INPUT!G5:G445)/D16,0)} -> 3.8392153 | F16: =IFERROR(B16/C16,0) -> 1854.5829
A17: =EDATE(A12,5) -> 45748 | B17: {=SUMPRODUCT((RAW_INPUT!A5:A445>=A17)*(RAW_INPUT!A5:A445<A18)*RAW_INPUT!G5:G445)} -> 34623.6 | C17: {=SUMPRODUCT((RAW_INPUT!A5:A445>=A17)*(RAW_INPUT!A5:A445<A18)*1)} -> 22 | D17: {=SUMPRODUCT((RAW_INPUT!A5:A445>=A17)*(RAW_INPUT!A5:A445<A18)*(RAW_INPUT!F5:F445<20)*RAW_INPUT!E5:E445)} -> 8091 | E17: {=IFERROR(SUMPRODUCT((RAW_INPUT!A5:A445>=A17)*(RAW_INPUT!A5:A445<A18)*(RAW_INPUT!F5:F445<20)*RAW_INPUT!G5:G445)/D17,0)} -> 3.7183846 | F17: =IFERROR(B17/C17,0) -> 1573.8
A18: =EDATE(A12,6) -> 45778 | B18: {=SUMPRODUCT((RAW_INPUT!A5:A445>=A18)*(RAW_INPUT!A5:A445<A19)*RAW_INPUT!G5:G445)} -> 31493.26 | C18: {=SUMPRODUCT((RAW_INPUT!A5:A445>=A18)*(RAW_INPUT!A5:A445<A19)*1)} -> 22 | D18: {=SUMPRODUCT((RAW_INPUT!A5:A445>=A18)*(RAW_INPUT!A5:A445<A19)*(RAW_INPUT!F5:F445<20)*RAW_INPUT!E5:E445)} -> 8007 | E18: {=IFERROR(SUMPRODUCT((RAW_INPUT!A5:A445>=A18)*(RAW_INPUT!A5:A445<A19)*(RAW_INPUT!F5:F445<20)*RAW_INPUT!G5:G445)/D18,0)} -> 3.4926352 | F18: =IFERROR(B18/C18,0) -> 1431.5118
A19: =EDATE(A12,7) -> 45809 | B19: {=SUMPRODUCT((RAW_INPUT!A5:A445>=A19)*(RAW_INPUT!A5:A445<A20)*RAW_INPUT!G5:G445)} -> 40666.24 | C19: {=SUMPRODUCT((RAW_INPUT!A5:A445>=A19)*(RAW_INPUT!A5:A445<A20)*1)} -> 21 | D19: {=SUMPRODUCT((RAW_INPUT!A5:A445>=A19)*(RAW_INPUT!A5:A445<A20)*(RAW_INPUT!F5:F445<20)*RAW_INPUT!E5:E445)} -> 9566 | E19: {=IFERROR(SUMPRODUCT((RAW_INPUT!A5:A445>=A19)*(RAW_INPUT!A5:A445<A20)*(RAW_INPUT!F5:F445<20)*RAW_INPUT!G5:G445)/D19,0)} -> 3.7048934 | F19: =IFERROR(B19/C19,0) -> 1936.4876
A20: =EDATE(A12,8) -> 45839 | B20: {=SUMPRODUCT((RAW_INPUT!A5:A445>=A20)*(RAW_INPUT!A5:A445<A21)*RAW_INPUT!G5:G445)} -> 51448.45 | C20: {=SUMPRODUCT((RAW_INPUT!A5:A445>=A20)*(RAW_INPUT!A5:A445<A21)*1)} -> 23 | D20: {=SUMPRODUCT((RAW_INPUT!A5:A445>=A20)*(RAW_INPUT!A5:A445<A21)*(RAW_INPUT!F5:F445<20)*RAW_INPUT!E5:E445)} -> 10000 | E20: {=IFERROR(SUMPRODUCT((RAW_INPUT!A5:A445>=A20)*(RAW_INPUT!A5:A445<A21)*(RAW_INPUT!F5:F445<20)*RAW_INPUT!G5:G445)/D20,0)} -> 3.840862 | F20: =IFERROR(B20/C20,0) -> 2236.8891
A21: =EDATE(A12,9) -> 45870 | B21: {=SUMPRODUCT((RAW_INPUT!A5:A445>=A21)*(RAW_INPUT!A5:A445<A22)*RAW_INPUT!G5:G445)} -> 34339.14 | C21: {=SUMPRODUCT((RAW_INPUT!A5:A445>=A21)*(RAW_INPUT!A5:A445<A22)*1)} -> 21 | D21: {=SUMPRODUCT((RAW_INPUT!A5:A445>=A21)*(RAW_INPUT!A5:A445<A22)*(RAW_INPUT!F5:F445<20)*RAW_INPUT!E5:E445)} -> 8294 | E21: {=IFERROR(SUMPRODUCT((RAW_INPUT!A5:A445>=A21)*(RAW_INPUT!A5:A445<A22)*(RAW_INPUT!F5:F445<20)*RAW_INPUT!G5:G445)/D21,0)} -> 3.7354425 | F21: =IFERROR(B21/C21,0) -> 1635.1971
A22: =EDATE(A12,10) -> 45901 | B22: {=SUMPRODUCT((RAW_INPUT!A5:A445>=A22)*(RAW_INPUT!A5:A445<A23)*RAW_INPUT!G5:G445)} -> 30597.68 | C22: {=SUMPRODUCT((RAW_INPUT!A5:A445>=A22)*(RAW_INPUT!A5:A445<A23)*1)} -> 22 | D22: {=SUMPRODUCT((RAW_INPUT!A5:A445>=A22)*(RAW_INPUT!A5:A445<A23)*(RAW_INPUT!F5:F445<20)*RAW_INPUT!E5:E445)} -> 7761 | E22: {=IFERROR(SUMPRODUCT((RAW_INPUT!A5:A445>=A22)*(RAW_INPUT!A5:A445<A23)*(RAW_INPUT!F5:F445<20)*RAW_INPUT!G5:G445)/D22,0)} -> 3.5220848 | F22: =IFERROR(B22/C22,0) -> 1390.8036
A23: =EDATE(A12,11) -> 45931 | B23: {=SUMPRODUCT((RAW_INPUT!A5:A445>=A23)*(RAW_INPUT!A5:A445<A24)*RAW_INPUT!G5:G445)} -> 42499.18 | C23: {=SUMPRODUCT((RAW_INPUT!A5:A445>=A23)*(RAW_INPUT!A5:A445<A24)*1)} -> 23 | D23: {=SUMPRODUCT((RAW_INPUT!A5:A445>=A23)*(RAW_INPUT!A5:A445<A24)*(RAW_INPUT!F5:F445<20)*RAW_INPUT!E5:E445)} -> 9880 | E23: {=IFERROR(SUMPRODUCT((RAW_INPUT!A5:A445>=A23)*(RAW_INPUT!A5:A445<A24)*(RAW_INPUT!F5:F445<20)*RAW_INPUT!G5:G445)/D23,0)} -> 3.6711559 | F23: =IFERROR(B23/C23,0) -> 1847.7904
A24: =EDATE(A12,12) -> 45962 | B24: {=SUMPRODUCT((RAW_INPUT!A5:A445>=A24)*(RAW_INPUT!A5:A445<A25)*RAW_INPUT!G5:G445)} -> 45169.68 | C24: {=SUMPRODUCT((RAW_INPUT!A5:A445>=A24)*(RAW_INPUT!A5:A445<A25)*1)} -> 20 | D24: {=SUMPRODUCT((RAW_INPUT!A5:A445>=A24)*(RAW_INPUT!A5:A445<A25)*(RAW_INPUT!F5:F445<20)*RAW_INPUT!E5:E445)} -> 8506 | E24: {=IFERROR(SUMPRODUCT((RAW_INPUT!A5:A445>=A24)*(RAW_INPUT!A5:A445<A25)*(RAW_INPUT!F5:F445<20)*RAW_INPUT!G5:G445)/D24,0)} -> 3.8284246 | F24: =IFERROR(B24/C24,0) -> 2258.484
A25: =EDATE(A12,13) -> 45992 | B25: {=SUMPRODUCT((RAW_INPUT!A5:A445>=A25)*(RAW_INPUT!A5:A445<A26)*RAW_INPUT!G5:G445)} -> 40036.92 | C25: {=SUMPRODUCT((RAW_INPUT!A5:A445>=A25)*(RAW_INPUT!A5:A445<A26)*1)} -> 23 | D25: {=SUMPRODUCT((RAW_INPUT!A5:A445>=A25)*(RAW_INPUT!A5:A445<A26)*(RAW_INPUT!F5:F445<20)*RAW_INPUT!E5:E445)} -> 10094 | E25: {=IFERROR(SUMPRODUCT((RAW_INPUT!A5:A445>=A25)*(RAW_INPUT!A5:A445<A26)*(RAW_INPUT!F5:F445<20)*RAW_INPUT!G5:G445)/D25,0)} -> 3.7634139 | F25: =IFERROR(B25/C25,0) -> 1740.7357
A26: =EDATE(A12,14) -> 46023 | B26: {=SUMPRODUCT((RAW_INPUT!A5:A445>=A26)*(RAW_INPUT!A5:A445<A27)*RAW_INPUT!G5:G445)} -> 31596 | C26: {=SUMPRODUCT((RAW_INPUT!A5:A445>=A26)*(RAW_INPUT!A5:A445<A27)*1)} -> 22 | D26: {=SUMPRODUCT((RAW_INPUT!A5:A445>=A26)*(RAW_INPUT!A5:A445<A27)*(RAW_INPUT!F5:F445<20)*RAW_INPUT!E5:E445)} -> 7521 | E26: {=IFERROR(SUMPRODUCT((RAW_INPUT!A5:A445>=A26)*(RAW_INPUT!A5:A445<A27)*(RAW_INPUT!F5:F445<20)*RAW_INPUT!G5:G445)/D26,0)} -> 3.5460484 | F26: =IFERROR(B26/C26,0) -> 1436.1818
A27: =EDATE(A12,15) -> 46054 | B27: {=SUMPRODUCT((RAW_INPUT!A5:A445>=A27)*(RAW_INPUT!A5:A445<A28)*RAW_INPUT!G5:G445)} -> 38335.35 | C27: {=SUMPRODUCT((RAW_INPUT!A5:A445>=A27)*(RAW_INPUT!A5:A445<A28)*1)} -> 20 | D27: {=SUMPRODUCT((RAW_INPUT!A5:A445>=A27)*(RAW_INPUT!A5:A445<A28)*(RAW_INPUT!F5:F445<20)*RAW_INPUT!E5:E445)} -> 9147 | E27: {=IFERROR(SUMPRODUCT((RAW_INPUT!A5:A445>=A27)*(RAW_INPUT!A5:A445<A28)*(RAW_INPUT!F5:F445<20)*RAW_INPUT!G5:G445)/D27,0)} -> 3.612227 | F27: =IFERROR(B27/C27,0) -> 1916.7675
A28: =EDATE(A12,16) -> 46082 | B28: {=SUMPRODUCT((RAW_INPUT!A5:A445>=A28)*(RAW_INPUT!A5:A445<A29)*RAW_INPUT!G5:G445)} -> 53895.36 | C28: {=SUMPRODUCT((RAW_INPUT!A5:A445>=A28)*(RAW_INPUT!A5:A445<A29)*1)} -> 22 | D28: {=SUMPRODUCT((RAW_INPUT!A5:A445>=A28)*(RAW_INPUT!A5:A445<A29)*(RAW_INPUT!F5:F445<20)*RAW_INPUT!E5:E445)} -> 10152 | E28: {=IFERROR(SUMPRODUCT((RAW_INPUT!A5:A445>=A28)*(RAW_INPUT!A5:A445<A29)*(RAW_INPUT!F5:F445<20)*RAW_INPUT!G5:G445)/D28,0)} -> 3.8064175 | F28: =IFERROR(B28/C28,0) -> 2449.7891
A29: =EDATE(A12,17) -> 46113 | B29: {=SUMPRODUCT((RAW_INPUT!A5:A445>=A29)*(RAW_INPUT!A5:A445<A30)*RAW_INPUT!G5:G445)} -> 39209.54 | C29: {=SUMPRODUCT((RAW_INPUT!A5:A445>=A29)*(RAW_INPUT!A5:A445<A30)*1)} -> 22 | D29: {=SUMPRODUCT((RAW_INPUT!A5:A445>=A29)*(RAW_INPUT!A5:A445<A30)*(RAW_INPUT!F5:F445<20)*RAW_INPUT!E5:E445)} -> 9733 | E29: {=IFERROR(SUMPRODUCT((RAW_INPUT!A5:A445>=A29)*(RAW_INPUT!A5:A445<A30)*(RAW_INPUT!F5:F445<20)*RAW_INPUT!G5:G445)/D29,0)} -> 3.8078105 | F29: =IFERROR(B29/C29,0) -> 1782.2518
A30: =EDATE(A12,18) -> 46143 | B30: {=SUMPRODUCT((RAW_INPUT!A5:A445>=A30)*(RAW_INPUT!A5:A445<A31)*RAW_INPUT!G5:G445)} -> 29912.14 | C30: {=SUMPRODUCT((RAW_INPUT!A5:A445>=A30)*(RAW_INPUT!A5:A445<A31)*1)} -> 21 | D30: {=SUMPRODUCT((RAW_INPUT!A5:A445>=A30)*(RAW_INPUT!A5:A445<A31)*(RAW_INPUT!F5:F445<20)*RAW_INPUT!E5:E445)} -> 7420 | E30: {=IFERROR(SUMPRODUCT((RAW_INPUT!A5:A445>=A30)*(RAW_INPUT!A5:A445<A31)*(RAW_INPUT!F5:F445<20)*RAW_INPUT!G5:G445)/D30,0)} -> 3.5973221 | F30: =IFERROR(B30/C30,0) -> 1424.3876
A31: =EDATE(A12,19) -> 46174 | B31: {=SUMPRODUCT((RAW_INPUT!A5:A445>=A31)*(RAW_INPUT!A5:A445<A32)*RAW_INPUT!G5:G445)} -> 40410.2 | C31: {=SUMPRODUCT((RAW_INPUT!A5:A445>=A31)*(RAW_INPUT!A5:A445<A32)*1)} -> 22 | D31: {=SUMPRODUCT((RAW_INPUT!A5:A445>=A31)*(RAW_INPUT!A5:A445<A32)*(RAW_INPUT!F5:F445<20)*RAW_INPUT!E5:E445)} -> 9498 | E31: {=IFERROR(SUMPRODUCT((RAW_INPUT!A5:A445>=A31)*(RAW_INPUT!A5:A445<A32)*(RAW_INPUT!F5:F445<20)*RAW_INPUT!G5:G445)/D31,0)} -> 3.5440187 | F31: =IFERROR(B31/C31,0) -> 1836.8273
A32: =EDATE(A12,20) -> 46204 | B32: {=SUMPRODUCT((RAW_INPUT!A5:A445>=A32)*(RAW_INPUT!A5:A445<EDATE(A32,1))*RAW_INPUT!G5:G445)} -> 37259.07 | C32: {=SUMPRODUCT((RAW_INPUT!A5:A445>=A32)*(RAW_INPUT!A5:A445<EDATE(A32,1))*1)} -> 15 | D32: {=SUMPRODUCT((RAW_INPUT!A5:A445>=A32)*(RAW_INPUT!A5:A445<EDATE(A32,1))*(RAW_INPUT!F5:F445<20)*RAW_INPUT!E5:E445)} -> 7158 | E32: {=IFERROR(SUMPRODUCT((RAW_INPUT!A5:A445>=A32)*(RAW_INPUT!A5:A445<EDATE(A32,1))*(RAW_INPUT!F5:F445<20)*RAW_INPUT!G5:G445)/D32,0)} -> 3.8134702 | F32: =IFERROR(B32/C32,0) -> 2483.938
A35: CUSTOMER ANALYSIS
A36: Customer | B36: Revenue | C36: % of Total | D36: # Transactions | E36: Avg Sale
A37: Acme Petroleum | B37: =SUMIF(RAW_INPUT!B5:B445,A37,RAW_INPUT!G5:G445) -> 41501.67 | C37: =B37/B$6 -> 0.052489902 | D37: =COUNTIF(RAW_INPUT!B5:B445,A37) -> 24 | E37: =IFERROR(B37/D37,0) -> 1729.2362
A38: Arkansas Valley Oil | B38: =SUMIF(RAW_INPUT!B5:B445,A38,RAW_INPUT!G5:G445) -> 61909.02 | C38: =B38/B$6 -> 0.078300425 | D38: =COUNTIF(RAW_INPUT!B5:B445,A38) -> 31 | E38: =IFERROR(B38/D38,0) -> 1997.0652
A39: Centennial Hauling | B39: =SUMIF(RAW_INPUT!B5:B445,A39,RAW_INPUT!G5:G445) -> 47913.34 | C39: =B39/B$6 -> 0.060599164 | D39: =COUNTIF(RAW_INPUT!B5:B445,A39) -> 30 | E39: =IFERROR(B39/D39,0) -> 1597.1113
A40: Colorado Fuel Corp | B40: =SUMIF(RAW_INPUT!B5:B445,A40,RAW_INPUT!G5:G445) -> 70383.26 | C40: =B40/B$6 -> 0.089018355 | D40: =COUNTIF(RAW_INPUT!B5:B445,A40) -> 37 | E40: =IFERROR(B40/D40,0) -> 1902.2503
A41: Front Range Inc | B41: =SUMIF(RAW_INPUT!B5:B445,A41,RAW_INPUT!G5:G445) -> 62231.92 | C41: =B41/B$6 -> 0.078708818 | D41: =COUNTIF(RAW_INPUT!B5:B445,A41) -> 34 | E41: =IFERROR(B41/D41,0) -> 1830.3506
A42: High Plains Co | B42: =SUMIF(RAW_INPUT!B5:B445,A42,RAW_INPUT!G5:G445) -> 40276.77 | C42: =B42/B$6 -> 0.05094069 | D42: =COUNTIF(RAW_INPUT!B5:B445,A42) -> 23 | E42: =IFERROR(B42/D42,0) -> 1751.1639
A43: Mesa Verde Logistics | B43: =SUMIF(RAW_INPUT!B5:B445,A43,RAW_INPUT!G5:G445) -> 65938.37 | C43: =B43/B$6 -> 0.08339661 | D43: =COUNTIF(RAW_INPUT!B5:B445,A43) -> 32 | E43: =IFERROR(B43/D43,0) -> 2060.5741
A44: Mountain View Fleet | B44: =SUMIF(RAW_INPUT!B5:B445,A44,RAW_INPUT!G5:G445) -> 44276.29 | C44: =B44/B$6 -> 0.055999147 | D44: =COUNTIF(RAW_INPUT!B5:B445,A44) -> 26 | E44: =IFERROR(B44/D44,0) -> 1702.9342
A45: Pikes Peak Energy | B45: =SUMIF(RAW_INPUT!B5:B445,A45,RAW_INPUT!G5:G445) -> 54238.65 | C45: =B45/B$6 -> 0.068599201 | D45: =COUNTIF(RAW_INPUT!B5:B445,A45) -> 31 | E45: =IFERROR(B45/D45,0) -> 1749.6339
A46: Pueblo Supply Chain | B46: =SUMIF(RAW_INPUT!B5:B445,A46,RAW_INPUT!G5:G445) -> 47618.62 | C46: =B46/B$6 -> 0.060226412 | D46: =COUNTIF(RAW_INPUT!B5:B445,A46) -> 28 | E46: =IFERROR(B46/D46,0) -> 1700.665
A47: Royal Gorge Freight | B47: =SUMIF(RAW_INPUT!B5:B445,A47,RAW_INPUT!G5:G445) -> 45844.21 | C47: =B47/B$6 -> 0.057982199 | D47: =COUNTIF(RAW_INPUT!B5:B445,A47) -> 27 | E47: =IFERROR(B47/D47,0) -> 1697.9337
A48: San Luis Transport | B48: =SUMIF(RAW_INPUT!B5:B445,A48,RAW_INPUT!G5:G445) -> 45275.31 | C48: =B48/B$6 -> 0.057262673 | D48: =COUNTIF(RAW_INPUT!B5:B445,A48) -> 30 | E48: =IFERROR(B48/D48,0) -> 1509.177
A49: Springs Delivery Co | B49: =SUMIF(RAW_INPUT!B5:B445,A49,RAW_INPUT!G5:G445) -> 38353.54 | C49: =B49/B$6 -> 0.048508254 | D49: =COUNTIF(RAW_INPUT!B5:B445,A49) -> 22 | E49: =IFERROR(B49/D49,0) -> 1743.3427
A50: Summit Logistics | B50: =SUMIF(RAW_INPUT!B5:B445,A50,RAW_INPUT!G5:G445) -> 74360.39 | C50: =B50/B$6 -> 0.094048494 | D50: =COUNTIF(RAW_INPUT!B5:B445,A50) -> 38 | E50: =IFERROR(B50/D50,0) -> 1956.8524
A51: Western Slope Transport | B51: =SUMIF(RAW_INPUT!B5:B445,A51,RAW_INPUT!G5:G445) -> 50538.72 | C51: =B51/B$6 -> 0.063919656 | D51: =COUNTIF(RAW_INPUT!B5:B445,A51) -> 28 | E51: =IFERROR(B51/D51,0) -> 1804.9543
A53: Top 5 Revenue Share | B53: =(LARGE(B37:B51,1)+LARGE(B37:B51,2)+LARGE(B37:B51,3)+LARGE(B37:B51,4)+LARGE(B37:B51,5))/B6 -> 0.4234727
A54: Median Revenue/Customer | B54: =MEDIAN(B37:B51) -> 47913.34
A55: Customer Count | B55: =COUNTA(A37:A51) -> 15
A57: PRODUCT & SERVICE BREAKDOWN
A58: Product / Service | B58: Revenue | C58: % of Total | D58: # Transactions | E58: Avg Qty | F58: Avg Price | H58: Services | I58: =B74 -> 87690.96
A59: Bulk Diesel | B59: =SUMIF(RAW_INPUT!D5:D445,A59,RAW_INPUT!G5:G445) -> 137376.79 | C59: =B59/B$6 -> 0.1737495 | D59: =COUNTIF(RAW_INPUT!D5:D445,A59) -> 74 | E59: =IFERROR(SUMIF(RAW_INPUT!D5:D445,A59,RAW_INPUT!E5:E445)/D59,0) -> 501.91892 | F59: =IFERROR(SUMIF(RAW_INPUT!D5:D445,A59,RAW_INPUT!F5:F445)/D59,0) -> 3.6881081 | H59: Specialty Products | I59: =B75 -> 32925
A60: Diesel Delivery | B60: =SUMIF(RAW_INPUT!D5:D445,A60,RAW_INPUT!G5:G445) -> 112467.38 | C60: =B60/B$6 -> 0.14224492 | D60: =COUNTIF(RAW_INPUT!D5:D445,A60) -> 63 | E60: =IFERROR(SUMIF(RAW_INPUT!D5:D445,A60,RAW_INPUT!E5:E445)/D60,0) -> 480.65079 | F60: =IFERROR(SUMIF(RAW_INPUT!D5:D445,A60,RAW_INPUT!F5:F445)/D60,0) -> 3.7065079
A61: Filter Service | B61: =SUMIF(RAW_INPUT!D5:D445,A61,RAW_INPUT!G5:G445) -> 22162.69 | C61: =B61/B$6 -> 0.028030617 | D61: =COUNTIF(RAW_INPUT!D5:D445,A61) -> 19 | E61: =IFERROR(SUMIF(RAW_INPUT!D5:D445,A61,RAW_INPUT!E5:E445)/D61,0) -> 1 | F61: =IFERROR(SUMIF(RAW_INPUT!D5:D445,A61,RAW_INPUT!F5:F445)/D61,0) -> 1166.4574
A62: Fleet Fuel Drop | B62: =SUMIF(RAW_INPUT!D5:D445,A62,RAW_INPUT!G5:G445) -> 144026.33 | C62: =B62/B$6 -> 0.18215961 | D62: =COUNTIF(RAW_INPUT!D5:D445,A62) -> 75 | E62: =IFERROR(SUMIF(RAW_INPUT!D5:D445,A62,RAW_INPUT!E5:E445)/D62,0) -> 516.74667 | F62: =IFERROR(SUMIF(RAW_INPUT!D5:D445,A62,RAW_INPUT!F5:F445)/D62,0) -> 3.7110667
A63: Line Flush Service | B63: =SUMIF(RAW_INPUT!D5:D445,A63,RAW_INPUT!G5:G445) -> 27346.15 | C63: =B63/B$6 -> 0.034586481 | D63: =COUNTIF(RAW_INPUT!D5:D445,A63) -> 22 | E63: =IFERROR(SUMIF(RAW_INPUT!D5:D445,A63,RAW_INPUT!E5:E445)/D63,0) -> 1 | F63: =IFERROR(SUMIF(RAW_INPUT!D5:D445,A63,RAW_INPUT!F5:F445)/D63,0) -> 1243.0068
A64: Lubricant Package | B64: =SUMIF(RAW_INPUT!D5:D445,A64,RAW_INPUT!G5:G445) -> 1080 | C64: =B64/B$6 -> 0.0013659473 | D64: =COUNTIF(RAW_INPUT!D5:D445,A64) -> 1 | E64: =IFERROR(SUMIF(RAW_INPUT!D5:D445,A64,RAW_INPUT!E5:E445)/D64,0) -> 24 | F64: =IFERROR(SUMIF(RAW_INPUT!D5:D445,A64,RAW_INPUT!F5:F445)/D64,0) -> 45
A65: Motor Oil Case | B65: =SUMIF(RAW_INPUT!D5:D445,A65,RAW_INPUT!G5:G445) -> 15322.6 | C65: =B65/B$6 -> 0.019379504 | D65: =COUNTIF(RAW_INPUT!D5:D445,A65) -> 2 | E65: =IFERROR(SUMIF(RAW_INPUT!D5:D445,A65,RAW_INPUT!E5:E445)/D65,0) -> 170 | F65: =IFERROR(SUMIF(RAW_INPUT!D5:D445,A65,RAW_INPUT!F5:F445)/D65,0) -> 45.07
A66: Premium Fuel Delivery | B66: =SUMIF(RAW_INPUT!D5:D445,A66,RAW_INPUT!G5:G445) -> 139607.8 | C66: =B66/B$6 -> 0.1765712 | D66: =COUNTIF(RAW_INPUT!D5:D445,A66) -> 79 | E66: =IFERROR(SUMIF(RAW_INPUT!D5:D445,A66,RAW_INPUT!E5:E445)/D66,0) -> 482.40506 | F66: =IFERROR(SUMIF(RAW_INPUT!D5:D445,A66,RAW_INPUT!F5:F445)/D66,0) -> 3.6563291
A67: Pump Maintenance | B67: =SUMIF(RAW_INPUT!D5:D445,A67,RAW_INPUT!G5:G445) -> 23147.98 | C67: =B67/B$6 -> 0.029276778 | D67: =COUNTIF(RAW_INPUT!D5:D445,A67) -> 19 | E67: =IFERROR(SUMIF(RAW_INPUT!D5:D445,A67,RAW_INPUT!E5:E445)/D67,0) -> 1 | F67: =IFERROR(SUMIF(RAW_INPUT!D5:D445,A67,RAW_INPUT!F5:F445)/D67,0) -> 1218.3147
A68: Synthetic Blend Package | B68: =SUMIF(RAW_INPUT!D5:D445,A68,RAW_INPUT!G5:G445) -> 16522.4 | C68: =B68/B$6 -> 0.02089697 | D68: =COUNTIF(RAW_INPUT!D5:D445,A68) -> 2 | E68: =IFERROR(SUMIF(RAW_INPUT!D5:D445,A68,RAW_INPUT!E5:E445)/D68,0) -> 182 | F68: =IFERROR(SUMIF(RAW_INPUT!D5:D445,A68,RAW_INPUT!F5:F445)/D68,0) -> 45.39
A69: Tank Inspection | B69: =SUMIF(RAW_INPUT!D5:D445,A69,RAW_INPUT!G5:G445) -> 15034.14 | C69: =B69/B$6 -> 0.019014669 | D69: =COUNTIF(RAW_INPUT!D5:D445,A69) -> 12 | E69: =IFERROR(SUMIF(RAW_INPUT!D5:D445,A69,RAW_INPUT!E5:E445)/D69,0) -> 1 | F69: =IFERROR(SUMIF(RAW_INPUT!D5:D445,A69,RAW_INPUT!F5:F445)/D69,0) -> 1252.845
A70: Unleaded Delivery | B70: =SUMIF(RAW_INPUT!D5:D445,A70,RAW_INPUT!G5:G445) -> 136565.82 | C70: =B70/B$6 -> 0.17272381 | D70: =COUNTIF(RAW_INPUT!D5:D445,A70) -> 73 | E70: =IFERROR(SUMIF(RAW_INPUT!D5:D445,A70,RAW_INPUT!E5:E445)/D70,0) -> 505.05479 | F70: =IFERROR(SUMIF(RAW_INPUT!D5:D445,A70,RAW_INPUT!F5:F445)/D70,0) -> 3.6943836
A72: CATEGORY SUMMARY
A73: Fuel Deliveries | B73: {=SUMPRODUCT((ISNUMBER(SEARCH("Delivery",RAW_INPUT!D5:D445))+ISNUMBER(SEARCH("Fuel Drop",RAW_INPUT!D5:D445))+ISNUMBER(SEARCH("Bulk Diesel",RAW_INPUT!D5:D445))>0)*RAW_INPUT!G5:G445)} -> 670044.12 | C73: =B73/B$6 -> 0.84744903
A74: Services | B74: {=SUMPRODUCT((ISNUMBER(SEARCH("Line Flush",RAW_INPUT!D5:D445))+ISNUMBER(SEARCH("Pump Maintenance",RAW_INPUT!D5:D445))+ISNUMBER(SEARCH("Tank Inspection",RAW_INPUT!D5:D445))+ISNUMBER(SEARCH("Filter Service",RAW_INPUT!D5:D445))>0)*RAW_INPUT!G5:G445)} -> 87690.96 | C74: =B74/B$6 -> 0.11090855
A75: Specialty Products | B75: {=SUMPRODUCT((ISNUMBER(SEARCH("Motor Oil",RAW_INPUT!D5:D445))+ISNUMBER(SEARCH("Lubricant",RAW_INPUT!D5:D445))+ISNUMBER(SEARCH("Synthetic",RAW_INPUT!D5:D445))>0)*RAW_INPUT!G5:G445)} -> 32925 | C75: =B75/B$6 -> 0.041642421
A78: PRICING TRENDS
A79: Month | B79: Avg Diesel $/Gal | C79: Avg Unleaded $/Gal | D79: Avg Premium $/Gal | E79: Avg Bulk $/Gal | F79: Avg Fleet $/Gal | G79: Overall Avg $/Gal | H79: Price Δ MoM
A80: =A12 -> 45597 | B80: {=IFERROR(SUMPRODUCT((RAW_INPUT!A5:A445>=A12)*(RAW_INPUT!A5:A445<A13)*(ISNUMBER(SEARCH("Diesel Delivery",RAW_INPUT!D5:D445)))*RAW_INPUT!F5:F445)/SUMPRODUCT((RAW_INPUT!A5:A445>=A12)*(RAW_INPUT!A5:A445<A13)*(ISNUMBER(SEARCH("Diesel Delivery",RAW_INPUT!D5:D445)))*1),"-")} -> 3.8228571 | C80: {=IFERROR(SUMPRODUCT((RAW_INPUT!A5:A445>=A12)*(RAW_INPUT!A5:A445<A13)*(ISNUMBER(SEARCH("Unleaded",RAW_INPUT!D5:D445)))*RAW_INPUT!F5:F445)/SUMPRODUCT((RAW_INPUT!A5:A445>=A12)*(RAW_INPUT!A5:A445<A13)*(ISNUMBER(SEARCH("Unleaded",RAW_INPUT!D5:D445)))*1),"-")} -> 3.85 | D80: {=IFERROR(SUMPRODUCT((RAW_INPUT!A5:A445>=A12)*(RAW_INPUT!A5:A445<A13)*(ISNUMBER(SEARCH("Premium",RAW_INPUT!D5:D445)))*RAW_INPUT!F5:F445)/SUMPRODUCT((RAW_INPUT!A5:A445>=A12)*(RAW_INPUT!A5:A445<A13)*(ISNUMBER(SEARCH("Premium",RAW_INPUT!D5:D445)))*1),"-")} -> 3.77 | E80: {=IFERROR(SUMPRODUCT((RAW_INPUT!A5:A445>=A12)*(RAW_INPUT!A5:A445<A13)*(ISNUMBER(SEARCH("Bulk",RAW_INPUT!D5:D445)))*RAW_INPUT!F5:F445)/SUMPRODUCT((RAW_INPUT!A5:A445>=A12)*(RAW_INPUT!A5:A445<A13)*(ISNUMBER(SEARCH("Bulk",RAW_INPUT!D5:D445)))*1),"-")} -> - | F80: {=IFERROR(SUMPRODUCT((RAW_INPUT!A5:A445>=A12)*(RAW_INPUT!A5:A445<A13)*(ISNUMBER(SEARCH("Fleet",RAW_INPUT!D5:D445)))*RAW_INPUT!F5:F445)/SUMPRODUCT((RAW_INPUT!A5:A445>=A12)*(RAW_INPUT!A5:A445<A13)*(ISNUMBER(SEARCH("Fleet",RAW_INPUT!D5:D445)))*1),"-")} -> 3.8033333 | G80: =E12 -> 3.8188107 | H80: -
A81: =A13 -> 45627 | B81: {=IFERROR(SUMPRODUCT((RAW_INPUT!A5:A445>=A13)*(RAW_INPUT!A5:A445<A14)*(ISNUMBER(SEARCH("Diesel Delivery",RAW_INPUT!D5:D445)))*RAW_INPUT!F5:F445)/SUMPRODUCT((RAW_INPUT!A5:A445>=A13)*(RAW_INPUT!A5:A445<A14)*(ISNUMBER(SEARCH("Diesel Delivery",RAW_INPUT!D5:D445)))*1),"-")} -> 3.658 | C81: {=IFERROR(SUMPRODUCT((RAW_INPUT!A5:A445>=A13)*(RAW_INPUT!A5:A445<A14)*(ISNUMBER(SEARCH("Unleaded",RAW_INPUT!D5:D445)))*RAW_INPUT!F5:F445)/SUMPRODUCT((RAW_INPUT!A5:A445>=A13)*(RAW_INPUT!A5:A445<A14)*(ISNUMBER(SEARCH("Unleaded",RAW_INPUT!D5:D445)))*1),"-")} -> 3.6133333 | D81: {=IFERROR(SUMPRODUCT((RAW_INPUT!A5:A445>=A13)*(RAW_INPUT!A5:A445<A14)*(ISNUMBER(SEARCH("Premium",RAW_INPUT!D5:D445)))*RAW_INPUT!F5:F445)/SUMPRODUCT((RAW_INPUT!A5:A445>=A13)*(RAW_INPUT!A5:A445<A14)*(ISNUMBER(SEARCH("Premium",RAW_INPUT!D5:D445)))*1),"-")} -> 3.64 | E81: {=IFERROR(SUMPRODUCT((RAW_INPUT!A5:A445>=A13)*(RAW_INPUT!A5:A445<A14)*(ISNUMBER(SEARCH("Bulk",RAW_INPUT!D5:D445)))*RAW_INPUT!F5:F445)/SUMPRODUCT((RAW_INPUT!A5:A445>=A13)*(RAW_INPUT!A5:A445<A14)*(ISNUMBER(SEARCH("Bulk",RAW_INPUT!D5:D445)))*1),"-")} -> 3.6233333 | F81: {=IFERROR(SUMPRODUCT((RAW_INPUT!A5:A445>=A13)*(RAW_INPUT!A5:A445<A14)*(ISNUMBER(SEARCH("Fleet",RAW_INPUT!D5:D445)))*RAW_INPUT!F5:F445)/SUMPRODUCT((RAW_INPUT!A5:A445>=A13)*(RAW_INPUT!A5:A445<A14)*(ISNUMBER(SEARCH("Fleet",RAW_INPUT!D5:D445)))*1),"-")} -> 3.66 | G81: =E13 -> 3.6529361 | H81: =IFERROR((G81-G80)/G80,"-") -> -0.043436186
A82: =A14 -> 45658 | B82: {=IFERROR(SUMPRODUCT((RAW_INPUT!A5:A445>=A14)*(RAW_INPUT!A5:A445<A15)*(ISNUMBER(SEARCH("Diesel Delivery",RAW_INPUT!D5:D445)))*RAW_INPUT!F5:F445)/SUMPRODUCT((RAW_INPUT!A5:A445>=A14)*(RAW_INPUT!A5:A445<A15)*(ISNUMBER(SEARCH("Diesel Delivery",RAW_INPUT!D5:D445)))*1),"-")} -> - | C82: {=IFERROR(SUMPRODUCT((RAW_INPUT!A5:A445>=A14)*(RAW_INPUT!A5:A445<A15)*(ISNUMBER(SEARCH("Unleaded",RAW_INPUT!D5:D445)))*RAW_INPUT!F5:F445)/SUMPRODUCT((RAW_INPUT!A5:A445>=A14)*(RAW_INPUT!A5:A445<A15)*(ISNUMBER(SEARCH("Unleaded",RAW_INPUT!D5:D445)))*1),"-")} -> 3.4666667 | D82: {=IFERROR(SUMPRODUCT((RAW_INPUT!A5:A445>=A14)*(RAW_INPUT!A5:A445<A15)*(ISNUMBER(SEARCH("Premium",RAW_INPUT!D5:D445)))*RAW_INPUT!F5:F445)/SUMPRODUCT((RAW_INPUT!A5:A445>=A14)*(RAW_INPUT!A5:A445<A15)*(ISNUMBER(SEARCH("Premium",RAW_INPUT!D5:D445)))*1),"-")} -> 3.46 | E82: {=IFERROR(SUMPRODUCT((RAW_INPUT!A5:A445>=A14)*(RAW_INPUT!A5:A445<A15)*(ISNUMBER(SEARCH("Bulk",RAW_INPUT!D5:D445)))*RAW_INPUT!F5:F445)/SUMPRODUCT((RAW_INPUT!A5:A445>=A14)*(RAW_INPUT!A5:A445<A15)*(ISNUMBER(SEARCH("Bulk",RAW_INPUT!D5:D445)))*1),"-")} -> 3.4 | F82: {=IFERROR(SUMPRODUCT((RAW_INPUT!A5:A445>=A14)*(RAW_INPUT!A5:A445<A15)*(ISNUMBER(SEARCH("Fleet",RAW_INPUT!D5:D445)))*RAW_INPUT!F5:F445)/SUMPRODUCT((RAW_INPUT!A5:A445>=A14)*(RAW_INPUT!A5:A445<A15)*(ISNUMBER(SEARCH("Fleet",RAW_INPUT!D5:D445)))*1),"-")} -> 3.455 | G82: =E14 -> 3.4524107 | H82: =IFERROR((G82-G81)/G81,"-") -> -0.054894331
A83: =A15 -> 45689 | B83: {=IFERROR(SUMPRODUCT((RAW_INPUT!A5:A445>=A15)*(RAW_INPUT!A5:A445<A16)*(ISNUMBER(SEARCH("Diesel Delivery",RAW_INPUT!D5:D445)))*RAW_INPUT!F5:F445)/SUMPRODUCT((RAW_INPUT!A5:A445>=A15)*(RAW_INPUT!A5:A445<A16)*(ISNUMBER(SEARCH("Diesel Delivery",RAW_INPUT!D5:D445)))*1),"-")} -> 3.824 | C83: {=IFERROR(SUMPRODUCT((RAW_INPUT!A5:A445>=A15)*(RAW_INPUT!A5:A445<A16)*(ISNUMBER(SEARCH("Unleaded",RAW_INPUT!D5:D445)))*RAW_INPUT!F5:F445)/SUMPRODUCT((RAW_INPUT!A5:A445>=A15)*(RAW_INPUT!A5:A445<A16)*(ISNUMBER(SEARCH("Unleaded",RAW_INPUT!D5:D445)))*1),"-")} -> 3.82 | D83: {=IFERROR(SUMPRODUCT((RAW_INPUT!A5:A445>=A15)*(RAW_INPUT!A5:A445<A16)*(ISNUMBER(SEARCH("Premium",RAW_INPUT!D5:D445)))*RAW_INPUT!F5:F445)/SUMPRODUCT((RAW_INPUT!A5:A445>=A15)*(RAW_INPUT!A5:A445<A16)*(ISNUMBER(SEARCH("Premium",RAW_INPUT!D5:D445)))*1),"-")} -> 3.77 | E83: {=IFERROR(SUMPRODUCT((RAW_INPUT!A5:A445>=A15)*(RAW_INPUT!A5:A445<A16)*(ISNUMBER(SEARCH("Bulk",RAW_INPUT!D5:D445)))*RAW_INPUT!F5:F445)/SUMPRODUCT((RAW_INPUT!A5:A445>=A15)*(RAW_INPUT!A5:A445<A16)*(ISNUMBER(SEARCH("Bulk",RAW_INPUT!D5:D445)))*1),"-")} -> 3.8133333 | F83: {=IFERROR(SUMPRODUCT((RAW_INPUT!A5:A445>=A15)*(RAW_INPUT!A5:A445<A16)*(ISNUMBER(SEARCH("Fleet",RAW_INPUT!D5:D445)))*RAW_INPUT!F5:F445)/SUMPRODUCT((RAW_INPUT!A5:A445>=A15)*(RAW_INPUT!A5:A445<A16)*(ISNUMBER(SEARCH("Fleet",RAW_INPUT!D5:D445)))*1),"-")} -> 3.8266667 | G83: =E15 -> 3.8136992 | H83: =IFERROR((G83-G82)/G82,"-") -> 0.10464818
A84: =A16 -> 45717 | B84: {=IFERROR(SUMPRODUCT((RAW_INPUT!A5:A445>=A16)*(RAW_INPUT!A5:A445<A17)*(ISNUMBER(SEARCH("Diesel Delivery",RAW_INPUT!D5:D445)))*RAW_INPUT!F5:F445)/SUMPRODUCT((RAW_INPUT!A5:A445>=A16)*(RAW_INPUT!A5:A445<A17)*(ISNUMBER(SEARCH("Diesel Delivery",RAW_INPUT!D5:D445)))*1),"-")} -> 3.8514286 | C84: {=IFERROR(SUMPRODUCT((RAW_INPUT!A5:A445>=A16)*(RAW_INPUT!A5:A445<A17)*(ISNUMBER(SEARCH("Unleaded",RAW_INPUT!D5:D445)))*RAW_INPUT!F5:F445)/SUMPRODUCT((RAW_INPUT!A5:A445>=A16)*(RAW_INPUT!A5:A445<A17)*(ISNUMBER(SEARCH("Unleaded",RAW_INPUT!D5:D445)))*1),"-")} -> 3.8533333 | D84: {=IFERROR(SUMPRODUCT((RAW_INPUT!A5:A445>=A16)*(RAW_INPUT!A5:A445<A17)*(ISNUMBER(SEARCH("Premium",RAW_INPUT!D5:D445)))*RAW_INPUT!F5:F445)/SUMPRODUCT((RAW_INPUT!A5:A445>=A16)*(RAW_INPUT!A5:A445<A17)*(ISNUMBER(SEARCH("Premium",RAW_INPUT!D5:D445)))*1),"-")} -> 3.85 | E84: {=IFERROR(SUMPRODUCT((RAW_INPUT!A5:A445>=A16)*(RAW_INPUT!A5:A445<A17)*(ISNUMBER(SEARCH("Bulk",RAW_INPUT!D5:D445)))*RAW_INPUT!F5:F445)/SUMPRODUCT((RAW_INPUT!A5:A445>=A16)*(RAW_INPUT!A5:A445<A17)*(ISNUMBER(SEARCH("Bulk",RAW_INPUT!D5:D445)))*1),"-")} -> 3.8 | F84: {=IFERROR(SUMPRODUCT((RAW_INPUT!A5:A445>=A16)*(RAW_INPUT!A5:A445<A17)*(ISNUMBER(SEARCH("Fleet",RAW_INPUT!D5:D445)))*RAW_INPUT!F5:F445)/SUMPRODUCT((RAW_INPUT!A5:A445>=A16)*(RAW_INPUT!A5:A445<A17)*(ISNUMBER(SEARCH("Fleet",RAW_INPUT!D5:D445)))*1),"-")} -> 3.828 | G84: =E16 -> 3.8392153 | H84: =IFERROR((G84-G83)/G83,"-") -> 0.0066906643
A85: =A17 -> 45748 | B85: {=IFERROR(SUMPRODUCT((RAW_INPUT!A5:A445>=A17)*(RAW_INPUT!A5:A445<A18)*(ISNUMBER(SEARCH("Diesel Delivery",RAW_INPUT!D5:D445)))*RAW_INPUT!F5:F445)/SUMPRODUCT((RAW_INPUT!A5:A445>=A17)*(RAW_INPUT!A5:A445<A18)*(ISNUMBER(SEARCH("Diesel Delivery",RAW_INPUT!D5:D445)))*1),"-")} -> 3.6866667 | C85: {=IFERROR(SUMPRODUCT((RAW_INPUT!A5:A445>=A17)*(RAW_INPUT!A5:A445<A18)*(ISNUMBER(SEARCH("Unleaded",RAW_INPUT!D5:D445)))*RAW_INPUT!F5:F445)/SUMPRODUCT((RAW_INPUT!A5:A445>=A17)*(RAW_INPUT!A5:A445<A18)*(ISNUMBER(SEARCH("Unleaded",RAW_INPUT!D5:D445)))*1),"-")} -> 3.718 | D85: {=IFERROR(SUMPRODUCT((RAW_INPUT!A5:A445>=A17)*(RAW_INPUT!A5:A445<A18)*(ISNUMBER(SEARCH("Premium",RAW_INPUT!D5:D445)))*RAW_INPUT!F5:F445)/SUMPRODUCT((RAW_INPUT!A5:A445>=A17)*(RAW_INPUT!A5:A445<A18)*(ISNUMBER(SEARCH("Premium",RAW_INPUT!D5:D445)))*1),"-")} -> 3.7116667 | E85: {=IFERROR(SUMPRODUCT((RAW_INPUT!A5:A445>=A17)*(RAW_INPUT!A5:A445<A18)*(ISNUMBER(SEARCH("Bulk",RAW_INPUT!D5:D445)))*RAW_INPUT!F5:F445)/SUMPRODUCT((RAW_INPUT!A5:A445>=A17)*(RAW_INPUT!A5:A445<A18)*(ISNUMBER(SEARCH("Bulk",RAW_INPUT!D5:D445)))*1),"-")} -> 3.76 | F85: {=IFERROR(SUMPRODUCT((RAW_INPUT!A5:A445>=A17)*(RAW_INPUT!A5:A445<A18)*(ISNUMBER(SEARCH("Fleet",RAW_INPUT!D5:D445)))*RAW_INPUT!F5:F445)/SUMPRODUCT((RAW_INPUT!A5:A445>=A17)*(RAW_INPUT!A5:A445<A18)*(ISNUMBER(SEARCH("Fleet",RAW_INPUT!D5:D445)))*1),"-")} -> 3.74 | G85: =E17 -> 3.7183846 | H85: =IFERROR((G85-G84)/G84,"-") -> -0.031472763
A86: =A18 -> 45778 | B86: {=IFERROR(SUMPRODUCT((RAW_INPUT!A5:A445>=A18)*(RAW_INPUT!A5:A445<A19)*(ISNUMBER(SEARCH("Diesel Delivery",RAW_INPUT!D5:D445)))*RAW_INPUT!F5:F445)/SUMPRODUCT((RAW_INPUT!A5:A445>=A18)*(RAW_INPUT!A5:A445<A19)*(ISNUMBER(SEARCH("Diesel Delivery",RAW_INPUT!D5:D445)))*1),"-")} -> 3.58 | C86: {=IFERROR(SUMPRODUCT((RAW_INPUT!A5:A445>=A18)*(RAW_INPUT!A5:A445<A19)*(ISNUMBER(SEARCH("Unleaded",RAW_INPUT!D5:D445)))*RAW_INPUT!F5:F445)/SUMPRODUCT((RAW_INPUT!A5:A445>=A18)*(RAW_INPUT!A5:A445<A19)*(ISNUMBER(SEARCH("Unleaded",RAW_INPUT!D5:D445)))*1),"-")} -> 3.4857143 | D86: {=IFERROR(SUMPRODUCT((RAW_INPUT!A5:A445>=A18)*(RAW_INPUT!A5:A445<A19)*(ISNUMBER(SEARCH("Premium",RAW_INPUT!D5:D445)))*RAW_INPUT!F5:F445)/SUMPRODUCT((RAW_INPUT!A5:A445>=A18)*(RAW_INPUT!A5:A445<A19)*(ISNUMBER(SEARCH("Premium",RAW_INPUT!D5:D445)))*1),"-")} -> 3.56 | E86: {=IFERROR(SUMPRODUCT((RAW_INPUT!A5:A445>=A18)*(RAW_INPUT!A5:A445<A19)*(ISNUMBER(SEARCH("Bulk",RAW_INPUT!D5:D445)))*RAW_INPUT!F5:F445)/SUMPRODUCT((RAW_INPUT!A5:A445>=A18)*(RAW_INPUT!A5:A445<A19)*(ISNUMBER(SEARCH("Bulk",RAW_INPUT!D5:D445)))*1),"-")} -> 3.5 | F86: {=IFERROR(SUMPRODUCT((RAW_INPUT!A5:A445>=A18)*(RAW_INPUT!A5:A445<A19)*(ISNUMBER(SEARCH("Fleet",RAW_INPUT!D5:D445)))*RAW_INPUT!F5:F445)/SUMPRODUCT((RAW_INPUT!A5:A445>=A18)*(RAW_INPUT!A5:A445<A19)*(ISNUMBER(SEARCH("Fleet",RAW_INPUT!D5:D445)))*1),"-")} -> 3.4766667 | G86: =E18 -> 3.4926352 | H86: =IFERROR((G86-G85)/G85,"-") -> -0.060711694
A87: =A19 -> 45809 | B87: {=IFERROR(SUMPRODUCT((RAW_INPUT!A5:A445>=A19)*(RAW_INPUT!A5:A445<A20)*(ISNUMBER(SEARCH("Diesel Delivery",RAW_INPUT!D5:D445)))*RAW_INPUT!F5:F445)/SUMPRODUCT((RAW_INPUT!A5:A445>=A19)*(RAW_INPUT!A5:A445<A20)*(ISNUMBER(SEARCH("Diesel Delivery",RAW_INPUT!D5:D445)))*1),"-")} -> 3.6 | C87: {=IFERROR(SUMPRODUCT((RAW_INPUT!A5:A445>=A19)*(RAW_INPUT!A5:A445<A20)*(ISNUMBER(SEARCH("Unleaded",RAW_INPUT!D5:D445)))*RAW_INPUT!F5:F445)/SUMPRODUCT((RAW_INPUT!A5:A445>=A19)*(RAW_INPUT!A5:A445<A20)*(ISNUMBER(SEARCH("Unleaded",RAW_INPUT!D5:D445)))*1),"-")} -> 3.615 | D87: {=IFERROR(SUMPRODUCT((RAW_INPUT!A5:A445>=A19)*(RAW_INPUT!A5:A445<A20)*(ISNUMBER(SEARCH("Premium",RAW_INPUT!D5:D445)))*RAW_INPUT!F5:F445)/SUMPRODUCT((RAW_INPUT!A5:A445>=A19)*(RAW_INPUT!A5:A445<A20)*(ISNUMBER(SEARCH("Premium",RAW_INPUT!D5:D445)))*1),"-")} -> 3.6433333 | E87: {=IFERROR(SUMPRODUCT((RAW_INPUT!A5:A445>=A19)*(RAW_INPUT!A5:A445<A20)*(ISNUMBER(SEARCH("Bulk",RAW_INPUT!D5:D445)))*RAW_INPUT!F5:F445)/SUMPRODUCT((RAW_INPUT!A5:A445>=A19)*(RAW_INPUT!A5:A445<A20)*(ISNUMBER(SEARCH("Bulk",RAW_INPUT!D5:D445)))*1),"-")} -> 3.7275 | F87: {=IFERROR(SUMPRODUCT((RAW_INPUT!A5:A445>=A19)*(RAW_INPUT!A5:A445<A20)*(ISNUMBER(SEARCH("Fleet",RAW_INPUT!D5:D445)))*RAW_INPUT!F5:F445)/SUMPRODUCT((RAW_INPUT!A5:A445>=A19)*(RAW_INPUT!A5:A445<A20)*(ISNUMBER(SEARCH("Fleet",RAW_INPUT!D5:D445)))*1),"-")} -> 3.7616667 | G87: =E19 -> 3.7048934 | H87: =IFERROR((G87-G86)/G86,"-") -> 0.060773074
A88: =A20 -> 45839 | B88: {=IFERROR(SUMPRODUCT((RAW_INPUT!A5:A445>=A20)*(RAW_INPUT!A5:A445<A21)*(ISNUMBER(SEARCH("Diesel Delivery",RAW_INPUT!D5:D445)))*RAW_INPUT!F5:F445)/SUMPRODUCT((RAW_INPUT!A5:A445>=A20)*(RAW_INPUT!A5:A445<A21)*(ISNUMBER(SEARCH("Diesel Delivery",RAW_INPUT!D5:D445)))*1),"-")} -> 3.85 | C88: {=IFERROR(SUMPRODUCT((RAW_INPUT!A5:A445>=A20)*(RAW_INPUT!A5:A445<A21)*(ISNUMBER(SEARCH("Unleaded",RAW_INPUT!D5:D445)))*RAW_INPUT!F5:F445)/SUMPRODUCT((RAW_INPUT!A5:A445>=A20)*(RAW_INPUT!A5:A445<A21)*(ISNUMBER(SEARCH("Unleaded",RAW_INPUT!D5:D445)))*1),"-")} -> 3.84 | D88: {=IFERROR(SUMPRODUCT((RAW_INPUT!A5:A445>=A20)*(RAW_INPUT!A5:A445<A21)*(ISNUMBER(SEARCH("Premium",RAW_INPUT!D5:D445)))*RAW_INPUT!F5:F445)/SUMPRODUCT((RAW_INPUT!A5:A445>=A20)*(RAW_INPUT!A5:A445<A21)*(ISNUMBER(SEARCH("Premium",RAW_INPUT!D5:D445)))*1),"-")} -> 3.88 | E88: {=IFERROR(SUMPRODUCT((RAW_INPUT!A5:A445>=A20)*(RAW_INPUT!A5:A445<A21)*(ISNUMBER(SEARCH("Bulk",RAW_INPUT!D5:D445)))*RAW_INPUT!F5:F445)/SUMPRODUCT((RAW_INPUT!A5:A445>=A20)*(RAW_INPUT!A5:A445<A21)*(ISNUMBER(SEARCH("Bulk",RAW_INPUT!D5:D445)))*1),"-")} -> 3.8833333 | F88: {=IFERROR(SUMPRODUCT((RAW_INPUT!A5:A445>=A20)*(RAW_INPUT!A5:A445<A21)*(ISNUMBER(SEARCH("Fleet",RAW_INPUT!D5:D445)))*RAW_INPUT!F5:F445)/SUMPRODUCT((RAW_INPUT!A5:A445>=A20)*(RAW_INPUT!A5:A445<A21)*(ISNUMBER(SEARCH("Fleet",RAW_INPUT!D5:D445)))*1),"-")} -> 3.8266667 | G88: =E20 -> 3.840862 | H88: =IFERROR((G88-G87)/G87,"-") -> 0.036699741
A89: =A21 -> 45870 | B89: {=IFERROR(SUMPRODUCT((RAW_INPUT!A5:A445>=A21)*(RAW_INPUT!A5:A445<A22)*(ISNUMBER(SEARCH("Diesel Delivery",RAW_INPUT!D5:D445)))*RAW_INPUT!F5:F445)/SUMPRODUCT((RAW_INPUT!A5:A445>=A21)*(RAW_INPUT!A5:A445<A22)*(ISNUMBER(SEARCH("Diesel Delivery",RAW_INPUT!D5:D445)))*1),"-")} -> - | C89: {=IFERROR(SUMPRODUCT((RAW_INPUT!A5:A445>=A21)*(RAW_INPUT!A5:A445<A22)*(ISNUMBER(SEARCH("Unleaded",RAW_INPUT!D5:D445)))*RAW_INPUT!F5:F445)/SUMPRODUCT((RAW_INPUT!A5:A445>=A21)*(RAW_INPUT!A5:A445<A22)*(ISNUMBER(SEARCH("Unleaded",RAW_INPUT!D5:D445)))*1),"-")} -> 3.785 | D89: {=IFERROR(SUMPRODUCT((RAW_INPUT!A5:A445>=A21)*(RAW_INPUT!A5:A445<A22)*(ISNUMBER(SEARCH("Premium",RAW_INPUT!D5:D445)))*RAW_INPUT!F5:F445)/SUMPRODUCT((RAW_INPUT!A5:A445>=A21)*(RAW_INPUT!A5:A445<A22)*(ISNUMBER(SEARCH("Premium",RAW_INPUT!D5:D445)))*1),"-")} -> 3.755 | E89: {=IFERROR(SUMPRODUCT((RAW_INPUT!A5:A445>=A21)*(RAW_INPUT!A5:A445<A22)*(ISNUMBER(SEARCH("Bulk",RAW_INPUT!D5:D445)))*RAW_INPUT!F5:F445)/SUMPRODUCT((RAW_INPUT!A5:A445>=A21)*(RAW_INPUT!A5:A445<A22)*(ISNUMBER(SEARCH("Bulk",RAW_INPUT!D5:D445)))*1),"-")} -> 3.7157143 | F89: {=IFERROR(SUMPRODUCT((RAW_INPUT!A5:A445>=A21)*(RAW_INPUT!A5:A445<A22)*(ISNUMBER(SEARCH("Fleet",RAW_INPUT!D5:D445)))*RAW_INPUT!F5:F445)/SUMPRODUCT((RAW_INPUT!A5:A445>=A21)*(RAW_INPUT!A5:A445<A22)*(ISNUMBER(SEARCH("Fleet",RAW_INPUT!D5:D445)))*1),"-")} -> 3.726 | G89: =E21 -> 3.7354425 | H89: =IFERROR((G89-G88)/G88,"-") -> -0.027446837
A90: =A22 -> 45901 | B90: {=IFERROR(SUMPRODUCT((RAW_INPUT!A5:A445>=A22)*(RAW_INPUT!A5:A445<A23)*(ISNUMBER(SEARCH("Diesel Delivery",RAW_INPUT!D5:D445)))*RAW_INPUT!F5:F445)/SUMPRODUCT((RAW_INPUT!A5:A445>=A22)*(RAW_INPUT!A5:A445<A23)*(ISNUMBER(SEARCH("Diesel Delivery",RAW_INPUT!D5:D445)))*1),"-")} -> 3.5325 | C90: {=IFERROR(SUMPRODUCT((RAW_INPUT!A5:A445>=A22)*(RAW_INPUT!A5:A445<A23)*(ISNUMBER(SEARCH("Unleaded",RAW_INPUT!D5:D445)))*RAW_INPUT!F5:F445)/SUMPRODUCT((RAW_INPUT!A5:A445>=A22)*(RAW_INPUT!A5:A445<A23)*(ISNUMBER(SEARCH("Unleaded",RAW_INPUT!D5:D445)))*1),"-")} -> 3.49 | D90: {=IFERROR(SUMPRODUCT((RAW_INPUT!A5:A445>=A22)*(RAW_INPUT!A5:A445<A23)*(ISNUMBER(SEARCH("Premium",RAW_INPUT!D5:D445)))*RAW_INPUT!F5:F445)/SUMPRODUCT((RAW_INPUT!A5:A445>=A22)*(RAW_INPUT!A5:A445<A23)*(ISNUMBER(SEARCH("Premium",RAW_INPUT!D5:D445)))*1),"-")} -> 3.53 | E90: {=IFERROR(SUMPRODUCT((RAW_INPUT!A5:A445>=A22)*(RAW_INPUT!A5:A445<A23)*(ISNUMBER(SEARCH("Bulk",RAW_INPUT!D5:D445)))*RAW_INPUT!F5:F445)/SUMPRODUCT((RAW_INPUT!A5:A445>=A22)*(RAW_INPUT!A5:A445<A23)*(ISNUMBER(SEARCH("Bulk",RAW_INPUT!D5:D445)))*1),"-")} -> 3.57 | F90: {=IFERROR(SUMPRODUCT((RAW_INPUT!A5:A445>=A22)*(RAW_INPUT!A5:A445<A23)*(ISNUMBER(SEARCH("Fleet",RAW_INPUT!D5:D445)))*RAW_INPUT!F5:F445)/SUMPRODUCT((RAW_INPUT!A5:A445>=A22)*(RAW_INPUT!A5:A445<A23)*(ISNUMBER(SEARCH("Fleet",RAW_INPUT!D5:D445)))*1),"-")} -> 3.52 | G90: =E22 -> 3.5220848 | H90: =IFERROR((G90-G89)/G89,"-") -> -0.057117117
A91: =A23 -> 45931 | B91: {=IFERROR(SUMPRODUCT((RAW_INPUT!A5:A445>=A23)*(RAW_INPUT!A5:A445<A24)*(ISNUMBER(SEARCH("Diesel Delivery",RAW_INPUT!D5:D445)))*RAW_INPUT!F5:F445)/SUMPRODUCT((RAW_INPUT!A5:A445>=A23)*(RAW_INPUT!A5:A445<A24)*(ISNUMBER(SEARCH("Diesel Delivery",RAW_INPUT!D5:D445)))*1),"-")} -> 3.65 | C91: {=IFERROR(SUMPRODUCT((RAW_INPUT!A5:A445>=A23)*(RAW_INPUT!A5:A445<A24)*(ISNUMBER(SEARCH("Unleaded",RAW_INPUT!D5:D445)))*RAW_INPUT!F5:F445)/SUMPRODUCT((RAW_INPUT!A5:A445>=A23)*(RAW_INPUT!A5:A445<A24)*(ISNUMBER(SEARCH("Unleaded",RAW_INPUT!D5:D445)))*1),"-")} -> 3.7075 | D91: {=IFERROR(SUMPRODUCT((RAW_INPUT!A5:A445>=A23)*(RAW_INPUT!A5:A445<A24)*(ISNUMBER(SEARCH("Premium",RAW_INPUT!D5:D445)))*RAW_INPUT!F5:F445)/SUMPRODUCT((RAW_INPUT!A5:A445>=A23)*(RAW_INPUT!A5:A445<A24)*(ISNUMBER(SEARCH("Premium",RAW_INPUT!D5:D445)))*1),"-")} -> 3.6388889 | E91: {=IFERROR(SUMPRODUCT((RAW_INPUT!A5:A445>=A23)*(RAW_INPUT!A5:A445<A24)*(ISNUMBER(SEARCH("Bulk",RAW_INPUT!D5:D445)))*RAW_INPUT!F5:F445)/SUMPRODUCT((RAW_INPUT!A5:A445>=A23)*(RAW_INPUT!A5:A445<A24)*(ISNUMBER(SEARCH("Bulk",RAW_INPUT!D5:D445)))*1),"-")} -> 3.59 | F91: {=IFERROR(SUMPRODUCT((RAW_INPUT!A5:A445>=A23)*(RAW_INPUT!A5:A445<A24)*(ISNUMBER(SEARCH("Fleet",RAW_INPUT!D5:D445)))*RAW_INPUT!F5:F445)/SUMPRODUCT((RAW_INPUT!A5:A445>=A23)*(RAW_INPUT!A5:A445<A24)*(ISNUMBER(SEARCH("Fleet",RAW_INPUT!D5:D445)))*1),"-")} -> 3.85 | G91: =E23 -> 3.6711559 | H91: =IFERROR((G91-G90)/G90,"-") -> 0.042324673
A92: =A24 -> 45962 | B92: {=IFERROR(SUMPRODUCT((RAW_INPUT!A5:A445>=A24)*(RAW_INPUT!A5:A445<A25)*(ISNUMBER(SEARCH("Diesel Delivery",RAW_INPUT!D5:D445)))*RAW_INPUT!F5:F445)/SUMPRODUCT((RAW_INPUT!A5:A445>=A24)*(RAW_INPUT!A5:A445<A25)*(ISNUMBER(SEARCH("Diesel Delivery",RAW_INPUT!D5:D445)))*1),"-")} -> 3.815 | C92: {=IFERROR(SUMPRODUCT((RAW_INPUT!A5:A445>=A24)*(RAW_INPUT!A5:A445<A25)*(ISNUMBER(SEARCH("Unleaded",RAW_INPUT!D5:D445)))*RAW_INPUT!F5:F445)/SUMPRODUCT((RAW_INPUT!A5:A445>=A24)*(RAW_INPUT!A5:A445<A25)*(ISNUMBER(SEARCH("Unleaded",RAW_INPUT!D5:D445)))*1),"-")} -> 3.86 | D92: {=IFERROR(SUMPRODUCT((RAW_INPUT!A5:A445>=A24)*(RAW_INPUT!A5:A445<A25)*(ISNUMBER(SEARCH("Premium",RAW_INPUT!D5:D445)))*RAW_INPUT!F5:F445)/SUMPRODUCT((RAW_INPUT!A5:A445>=A24)*(RAW_INPUT!A5:A445<A25)*(ISNUMBER(SEARCH("Premium",RAW_INPUT!D5:D445)))*1),"-")} -> 3.78 | E92: {=IFERROR(SUMPRODUCT((RAW_INPUT!A5:A445>=A24)*(RAW_INPUT!A5:A445<A25)*(ISNUMBER(SEARCH("Bulk",RAW_INPUT!D5:D445)))*RAW_INPUT!F5:F445)/SUMPRODUCT((RAW_INPUT!A5:A445>=A24)*(RAW_INPUT!A5:A445<A25)*(ISNUMBER(SEARCH("Bulk",RAW_INPUT!D5:D445)))*1),"-")} -> 3.86 | F92: {=IFERROR(SUMPRODUCT((RAW_INPUT!A5:A445>=A24)*(RAW_INPUT!A5:A445<A25)*(ISNUMBER(SEARCH("Fleet",RAW_INPUT!D5:D445)))*RAW_INPUT!F5:F445)/SUMPRODUCT((RAW_INPUT!A5:A445>=A24)*(RAW_INPUT!A5:A445<A25)*(ISNUMBER(SEARCH("Fleet",RAW_INPUT!D5:D445)))*1),"-")} -> 3.815 | G92: =E24 -> 3.8284246 | H92: =IFERROR((G92-G91)/G91,"-") -> 0.042839034
A93: =A25 -> 45992 | B93: {=IFERROR(SUMPRODUCT((RAW_INPUT!A5:A445>=A25)*(RAW_INPUT!A5:A445<A26)*(ISNUMBER(SEARCH("Diesel Delivery",RAW_INPUT!D5:D445)))*RAW_INPUT!F5:F445)/SUMPRODUCT((RAW_INPUT!A5:A445>=A25)*(RAW_INPUT!A5:A445<A26)*(ISNUMBER(SEARCH("Diesel Delivery",RAW_INPUT!D5:D445)))*1),"-")} -> 3.775 | C93: {=IFERROR(SUMPRODUCT((RAW_INPUT!A5:A445>=A25)*(RAW_INPUT!A5:A445<A26)*(ISNUMBER(SEARCH("Unleaded",RAW_INPUT!D5:D445)))*RAW_INPUT!F5:F445)/SUMPRODUCT((RAW_INPUT!A5:A445>=A25)*(RAW_INPUT!A5:A445<A26)*(ISNUMBER(SEARCH("Unleaded",RAW_INPUT!D5:D445)))*1),"-")} -> 3.7275 | D93: {=IFERROR(SUMPRODUCT((RAW_INPUT!A5:A445>=A25)*(RAW_INPUT!A5:A445<A26)*(ISNUMBER(SEARCH("Premium",RAW_INPUT!D5:D445)))*RAW_INPUT!F5:F445)/SUMPRODUCT((RAW_INPUT!A5:A445>=A25)*(RAW_INPUT!A5:A445<A26)*(ISNUMBER(SEARCH("Premium",RAW_INPUT!D5:D445)))*1),"-")} -> 3.7233333 | E93: {=IFERROR(SUMPRODUCT((RAW_INPUT!A5:A445>=A25)*(RAW_INPUT!A5:A445<A26)*(ISNUMBER(SEARCH("Bulk",RAW_INPUT!D5:D445)))*RAW_INPUT!F5:F445)/SUMPRODUCT((RAW_INPUT!A5:A445>=A25)*(RAW_INPUT!A5:A445<A26)*(ISNUMBER(SEARCH("Bulk",RAW_INPUT!D5:D445)))*1),"-")} -> 3.786 | F93: {=IFERROR(SUMPRODUCT((RAW_INPUT!A5:A445>=A25)*(RAW_INPUT!A5:A445<A26)*(ISNUMBER(SEARCH("Fleet",RAW_INPUT!D5:D445)))*RAW_INPUT!F5:F445)/SUMPRODUCT((RAW_INPUT!A5:A445>=A25)*(RAW_INPUT!A5:A445<A26)*(ISNUMBER(SEARCH("Fleet",RAW_INPUT!D5:D445)))*1),"-")} -> 3.7933333 | G93: =E25 -> 3.7634139 | H93: =IFERROR((G93-G92)/G92,"-") -> -0.016981066
A94: =A26 -> 46023 | B94: {=IFERROR(SUMPRODUCT((RAW_INPUT!A5:A445>=A26)*(RAW_INPUT!A5:A445<A27)*(ISNUMBER(SEARCH("Diesel Delivery",RAW_INPUT!D5:D445)))*RAW_INPUT!F5:F445)/SUMPRODUCT((RAW_INPUT!A5:A445>=A26)*(RAW_INPUT!A5:A445<A27)*(ISNUMBER(SEARCH("Diesel Delivery",RAW_INPUT!D5:D445)))*1),"-")} -> 3.54 | C94: {=IFERROR(SUMPRODUCT((RAW_INPUT!A5:A445>=A26)*(RAW_INPUT!A5:A445<A27)*(ISNUMBER(SEARCH("Unleaded",RAW_INPUT!D5:D445)))*RAW_INPUT!F5:F445)/SUMPRODUCT((RAW_INPUT!A5:A445>=A26)*(RAW_INPUT!A5:A445<A27)*(ISNUMBER(SEARCH("Unleaded",RAW_INPUT!D5:D445)))*1),"-")} -> 3.54 | D94: {=IFERROR(SUMPRODUCT((RAW_INPUT!A5:A445>=A26)*(RAW_INPUT!A5:A445<A27)*(ISNUMBER(SEARCH("Premium",RAW_INPUT!D5:D445)))*RAW_INPUT!F5:F445)/SUMPRODUCT((RAW_INPUT!A5:A445>=A26)*(RAW_INPUT!A5:A445<A27)*(ISNUMBER(SEARCH("Premium",RAW_INPUT!D5:D445)))*1),"-")} -> 3.608 | E94: {=IFERROR(SUMPRODUCT((RAW_INPUT!A5:A445>=A26)*(RAW_INPUT!A5:A445<A27)*(ISNUMBER(SEARCH("Bulk",RAW_INPUT!D5:D445)))*RAW_INPUT!F5:F445)/SUMPRODUCT((RAW_INPUT!A5:A445>=A26)*(RAW_INPUT!A5:A445<A27)*(ISNUMBER(SEARCH("Bulk",RAW_INPUT!D5:D445)))*1),"-")} -> 3.5242857 | F94: {=IFERROR(SUMPRODUCT((RAW_INPUT!A5:A445>=A26)*(RAW_INPUT!A5:A445<A27)*(ISNUMBER(SEARCH("Fleet",RAW_INPUT!D5:D445)))*RAW_INPUT!F5:F445)/SUMPRODUCT((RAW_INPUT!A5:A445>=A26)*(RAW_INPUT!A5:A445<A27)*(ISNUMBER(SEARCH("Fleet",RAW_INPUT!D5:D445)))*1),"-")} -> 3.545 | G94: =E26 -> 3.5460484 | H94: =IFERROR((G94-G93)/G93,"-") -> -0.057757535
A95: =A27 -> 46054 | B95: {=IFERROR(SUMPRODUCT((RAW_INPUT!A5:A445>=A27)*(RAW_INPUT!A5:A445<A28)*(ISNUMBER(SEARCH("Diesel Delivery",RAW_INPUT!D5:D445)))*RAW_INPUT!F5:F445)/SUMPRODUCT((RAW_INPUT!A5:A445>=A27)*(RAW_INPUT!A5:A445<A28)*(ISNUMBER(SEARCH("Diesel Delivery",RAW_INPUT!D5:D445)))*1),"-")} -> 3.3866667 | C95: {=IFERROR(SUMPRODUCT((RAW_INPUT!A5:A445>=A27)*(RAW_INPUT!A5:A445<A28)*(ISNUMBER(SEARCH("Unleaded",RAW_INPUT!D5:D445)))*RAW_INPUT!F5:F445)/SUMPRODUCT((RAW_INPUT!A5:A445>=A27)*(RAW_INPUT!A5:A445<A28)*(ISNUMBER(SEARCH("Unleaded",RAW_INPUT!D5:D445)))*1),"-")} -> 3.7133333 | D95: {=IFERROR(SUMPRODUCT((RAW_INPUT!A5:A445>=A27)*(RAW_INPUT!A5:A445<A28)*(ISNUMBER(SEARCH("Premium",RAW_INPUT!D5:D445)))*RAW_INPUT!F5:F445)/SUMPRODUCT((RAW_INPUT!A5:A445>=A27)*(RAW_INPUT!A5:A445<A28)*(ISNUMBER(SEARCH("Premium",RAW_INPUT!D5:D445)))*1),"-")} -> 3.83 | E95: {=IFERROR(SUMPRODUCT((RAW_INPUT!A5:A445>=A27)*(RAW_INPUT!A5:A445<A28)*(ISNUMBER(SEARCH("Bulk",RAW_INPUT!D5:D445)))*RAW_INPUT!F5:F445)/SUMPRODUCT((RAW_INPUT!A5:A445>=A27)*(RAW_INPUT!A5:A445<A28)*(ISNUMBER(SEARCH("Bulk",RAW_INPUT!D5:D445)))*1),"-")} -> 3.686 | F95: {=IFERROR(SUMPRODUCT((RAW_INPUT!A5:A445>=A27)*(RAW_INPUT!A5:A445<A28)*(ISNUMBER(SEARCH("Fleet",RAW_INPUT!D5:D445)))*RAW_INPUT!F5:F445)/SUMPRODUCT((RAW_INPUT!A5:A445>=A27)*(RAW_INPUT!A5:A445<A28)*(ISNUMBER(SEARCH("Fleet",RAW_INPUT!D5:D445)))*1),"-")} -> 3.5175 | G95: =E27 -> 3.612227 | H95: =IFERROR((G95-G94)/G94,"-") -> 0.018662622
A96: =A28 -> 46082 | B96: {=IFERROR(SUMPRODUCT((RAW_INPUT!A5:A445>=A28)*(RAW_INPUT!A5:A445<A29)*(ISNUMBER(SEARCH("Diesel Delivery",RAW_INPUT!D5:D445)))*RAW_INPUT!F5:F445)/SUMPRODUCT((RAW_INPUT!A5:A445>=A28)*(RAW_INPUT!A5:A445<A29)*(ISNUMBER(SEARCH("Diesel Delivery",RAW_INPUT!D5:D445)))*1),"-")} -> - | C96: {=IFERROR(SUMPRODUCT((RAW_INPUT!A5:A445>=A28)*(RAW_INPUT!A5:A445<A29)*(ISNUMBER(SEARCH("Unleaded",RAW_INPUT!D5:D445)))*RAW_INPUT!F5:F445)/SUMPRODUCT((RAW_INPUT!A5:A445>=A28)*(RAW_INPUT!A5:A445<A29)*(ISNUMBER(SEARCH("Unleaded",RAW_INPUT!D5:D445)))*1),"-")} -> 3.8025 | D96: {=IFERROR(SUMPRODUCT((RAW_INPUT!A5:A445>=A28)*(RAW_INPUT!A5:A445<A29)*(ISNUMBER(SEARCH("Premium",RAW_INPUT!D5:D445)))*RAW_INPUT!F5:F445)/SUMPRODUCT((RAW_INPUT!A5:A445>=A28)*(RAW_INPUT!A5:A445<A29)*(ISNUMBER(SEARCH("Premium",RAW_INPUT!D5:D445)))*1),"-")} -> 3.765 | E96: {=IFERROR(SUMPRODUCT((RAW_INPUT!A5:A445>=A28)*(RAW_INPUT!A5:A445<A29)*(ISNUMBER(SEARCH("Bulk",RAW_INPUT!D5:D445)))*RAW_INPUT!F5:F445)/SUMPRODUCT((RAW_INPUT!A5:A445>=A28)*(RAW_INPUT!A5:A445<A29)*(ISNUMBER(SEARCH("Bulk",RAW_INPUT!D5:D445)))*1),"-")} -> 3.8157143 | F96: {=IFERROR(SUMPRODUCT((RAW_INPUT!A5:A445>=A28)*(RAW_INPUT!A5:A445<A29)*(ISNUMBER(SEARCH("Fleet",RAW_INPUT!D5:D445)))*RAW_INPUT!F5:F445)/SUMPRODUCT((RAW_INPUT!A5:A445>=A28)*(RAW_INPUT!A5:A445<A29)*(ISNUMBER(SEARCH("Fleet",RAW_INPUT!D5:D445)))*1),"-")} -> 3.8266667 | G96: =E28 -> 3.8064175 | H96: =IFERROR((G96-G95)/G95,"-") -> 0.053759218
A97: =A29 -> 46113 | B97: {=IFERROR(SUMPRODUCT((RAW_INPUT!A5:A445>=A29)*(RAW_INPUT!A5:A445<A30)*(ISNUMBER(SEARCH("Diesel Delivery",RAW_INPUT!D5:D445)))*RAW_INPUT!F5:F445)/SUMPRODUCT((RAW_INPUT!A5:A445>=A29)*(RAW_INPUT!A5:A445<A30)*(ISNUMBER(SEARCH("Diesel Delivery",RAW_INPUT!D5:D445)))*1),"-")} -> 3.8133333 | C97: {=IFERROR(SUMPRODUCT((RAW_INPUT!A5:A445>=A29)*(RAW_INPUT!A5:A445<A30)*(ISNUMBER(SEARCH("Unleaded",RAW_INPUT!D5:D445)))*RAW_INPUT!F5:F445)/SUMPRODUCT((RAW_INPUT!A5:A445>=A29)*(RAW_INPUT!A5:A445<A30)*(ISNUMBER(SEARCH("Unleaded",RAW_INPUT!D5:D445)))*1),"-")} -> 3.8133333 | D97: {=IFERROR(SUMPRODUCT((RAW_INPUT!A5:A445>=A29)*(RAW_INPUT!A5:A445<A30)*(ISNUMBER(SEARCH("Premium",RAW_INPUT!D5:D445)))*RAW_INPUT!F5:F445)/SUMPRODUCT((RAW_INPUT!A5:A445>=A29)*(RAW_INPUT!A5:A445<A30)*(ISNUMBER(SEARCH("Premium",RAW_INPUT!D5:D445)))*1),"-")} -> 3.82125 | E97: {=IFERROR(SUMPRODUCT((RAW_INPUT!A5:A445>=A29)*(RAW_INPUT!A5:A445<A30)*(ISNUMBER(SEARCH("Bulk",RAW_INPUT!D5:D445)))*RAW_INPUT!F5:F445)/SUMPRODUCT((RAW_INPUT!A5:A445>=A29)*(RAW_INPUT!A5:A445<A30)*(ISNUMBER(SEARCH("Bulk",RAW_INPUT!D5:D445)))*1),"-")} -> 3.8 | F97: {=IFERROR(SUMPRODUCT((RAW_INPUT!A5:A445>=A29)*(RAW_INPUT!A5:A445<A30)*(ISNUMBER(SEARCH("Fleet",RAW_INPUT!D5:D445)))*RAW_INPUT!F5:F445)/SUMPRODUCT((RAW_INPUT!A5:A445>=A29)*(RAW_INPUT!A5:A445<A30)*(ISNUMBER(SEARCH("Fleet",RAW_INPUT!D5:D445)))*1),"-")} -> 3.7566667 | G97: =E29 -> 3.8078105 | H97: =IFERROR((G97-G96)/G96,"-") -> 0.00036598371
A98: =A30 -> 46143 | B98: {=IFERROR(SUMPRODUCT((RAW_INPUT!A5:A445>=A30)*(RAW_INPUT!A5:A445<A31)*(ISNUMBER(SEARCH("Diesel Delivery",RAW_INPUT!D5:D445)))*RAW_INPUT!F5:F445)/SUMPRODUCT((RAW_INPUT!A5:A445>=A30)*(RAW_INPUT!A5:A445<A31)*(ISNUMBER(SEARCH("Diesel Delivery",RAW_INPUT!D5:D445)))*1),"-")} -> 3.63 | C98: {=IFERROR(SUMPRODUCT((RAW_INPUT!A5:A445>=A30)*(RAW_INPUT!A5:A445<A31)*(ISNUMBER(SEARCH("Unleaded",RAW_INPUT!D5:D445)))*RAW_INPUT!F5:F445)/SUMPRODUCT((RAW_INPUT!A5:A445>=A30)*(RAW_INPUT!A5:A445<A31)*(ISNUMBER(SEARCH("Unleaded",RAW_INPUT!D5:D445)))*1),"-")} -> 3.6125 | D98: {=IFERROR(SUMPRODUCT((RAW_INPUT!A5:A445>=A30)*(RAW_INPUT!A5:A445<A31)*(ISNUMBER(SEARCH("Premium",RAW_INPUT!D5:D445)))*RAW_INPUT!F5:F445)/SUMPRODUCT((RAW_INPUT!A5:A445>=A30)*(RAW_INPUT!A5:A445<A31)*(ISNUMBER(SEARCH("Premium",RAW_INPUT!D5:D445)))*1),"-")} -> 3.5766667 | E98: {=IFERROR(SUMPRODUCT((RAW_INPUT!A5:A445>=A30)*(RAW_INPUT!A5:A445<A31)*(ISNUMBER(SEARCH("Bulk",RAW_INPUT!D5:D445)))*RAW_INPUT!F5:F445)/SUMPRODUCT((RAW_INPUT!A5:A445>=A30)*(RAW_INPUT!A5:A445<A31)*(ISNUMBER(SEARCH("Bulk",RAW_INPUT!D5:D445)))*1),"-")} -> 3.5675 | F98: {=IFERROR(SUMPRODUCT((RAW_INPUT!A5:A445>=A30)*(RAW_INPUT!A5:A445<A31)*(ISNUMBER(SEARCH("Fleet",RAW_INPUT!D5:D445)))*RAW_INPUT!F5:F445)/SUMPRODUCT((RAW_INPUT!A5:A445>=A30)*(RAW_INPUT!A5:A445<A31)*(ISNUMBER(SEARCH("Fleet",RAW_INPUT!D5:D445)))*1),"-")} -> 3.62 | G98: =E30 -> 3.5973221 | H98: =IFERROR((G98-G97)/G97,"-") -> -0.055278076
A99: =A31 -> 46174 | B99: {=IFERROR(SUMPRODUCT((RAW_INPUT!A5:A445>=A31)*(RAW_INPUT!A5:A445<A32)*(ISNUMBER(SEARCH("Diesel Delivery",RAW_INPUT!D5:D445)))*RAW_INPUT!F5:F445)/SUMPRODUCT((RAW_INPUT!A5:A445>=A31)*(RAW_INPUT!A5:A445<A32)*(ISNUMBER(SEARCH("Diesel Delivery",RAW_INPUT!D5:D445)))*1),"-")} -> 3.42 | C99: {=IFERROR(SUMPRODUCT((RAW_INPUT!A5:A445>=A31)*(RAW_INPUT!A5:A445<A32)*(ISNUMBER(SEARCH("Unleaded",RAW_INPUT!D5:D445)))*RAW_INPUT!F5:F445)/SUMPRODUCT((RAW_INPUT!A5:A445>=A31)*(RAW_INPUT!A5:A445<A32)*(ISNUMBER(SEARCH("Unleaded",RAW_INPUT!D5:D445)))*1),"-")} -> 3.5125 | D99: {=IFERROR(SUMPRODUCT((RAW_INPUT!A5:A445>=A31)*(RAW_INPUT!A5:A445<A32)*(ISNUMBER(SEARCH("Premium",RAW_INPUT!D5:D445)))*RAW_INPUT!F5:F445)/SUMPRODUCT((RAW_INPUT!A5:A445>=A31)*(RAW_INPUT!A5:A445<A32)*(ISNUMBER(SEARCH("Premium",RAW_INPUT!D5:D445)))*1),"-")} -> 3.5333333 | E99: {=IFERROR(SUMPRODUCT((RAW_INPUT!A5:A445>=A31)*(RAW_INPUT!A5:A445<A32)*(ISNUMBER(SEARCH("Bulk",RAW_INPUT!D5:D445)))*RAW_INPUT!F5:F445)/SUMPRODUCT((RAW_INPUT!A5:A445>=A31)*(RAW_INPUT!A5:A445<A32)*(ISNUMBER(SEARCH("Bulk",RAW_INPUT!D5:D445)))*1),"-")} -> 3.5866667 | F99: {=IFERROR(SUMPRODUCT((RAW_INPUT!A5:A445>=A31)*(RAW_INPUT!A5:A445<A32)*(ISNUMBER(SEARCH("Fleet",RAW_INPUT!D5:D445)))*RAW_INPUT!F5:F445)/SUMPRODUCT((RAW_INPUT!A5:A445>=A31)*(RAW_INPUT!A5:A445<A32)*(ISNUMBER(SEARCH("Fleet",RAW_INPUT!D5:D445)))*1),"-")} -> 3.64 | G99: =E31 -> 3.5440187 | H99: =IFERROR((G99-G98)/G98,"-") -> -0.014817512
A100: =A32 -> 46204 | B100: {=IFERROR(SUMPRODUCT((RAW_INPUT!A5:A445>=A32)*(RAW_INPUT!A5:A445<EDATE(A32,1))*(ISNUMBER(SEARCH("Diesel Delivery",RAW_INPUT!D5:D445)))*RAW_INPUT!F5:F445)/SUMPRODUCT((RAW_INPUT!A5:A445>=A32)*(RAW_INPUT!A5:A445<EDATE(A32,1))*(ISNUMBER(SEARCH("Diesel Delivery",RAW_INPUT!D5:D445)))*1),"-")} -> 3.8 | C100: {=IFERROR(SUMPRODUCT((RAW_INPUT!A5:A445>=A32)*(RAW_INPUT!A5:A445<EDATE(A32,1))*(ISNUMBER(SEARCH("Unleaded",RAW_INPUT!D5:D445)))*RAW_INPUT!F5:F445)/SUMPRODUCT((RAW_INPUT!A5:A445>=A32)*(RAW_INPUT!A5:A445<EDATE(A32,1))*(ISNUMBER(SEARCH("Unleaded",RAW_INPUT!D5:D445)))*1),"-")} -> 3.8125 | D100: {=IFERROR(SUMPRODUCT((RAW_INPUT!A5:A445>=A32)*(RAW_INPUT!A5:A445<EDATE(A32,1))*(ISNUMBER(SEARCH("Premium",RAW_INPUT!D5:D445)))*RAW_INPUT!F5:F445)/SUMPRODUCT((RAW_INPUT!A5:A445>=A32)*(RAW_INPUT!A5:A445<EDATE(A32,1))*(ISNUMBER(SEARCH("Premium",RAW_INPUT!D5:D445)))*1),"-")} -> 3.79 | E100: {=IFERROR(SUMPRODUCT((RAW_INPUT!A5:A445>=A32)*(RAW_INPUT!A5:A445<EDATE(A32,1))*(ISNUMBER(SEARCH("Bulk",RAW_INPUT!D5:D445)))*RAW_INPUT!F5:F445)/SUMPRODUCT((RAW_INPUT!A5:A445>=A32)*(RAW_INPUT!A5:A445<EDATE(A32,1))*(ISNUMBER(SEARCH("Bulk",RAW_INPUT!D5:D445)))*1),"-")} -> 3.75 | F100: {=IFERROR(SUMPRODUCT((RAW_INPUT!A5:A445>=A32)*(RAW_INPUT!A5:A445<EDATE(A32,1))*(ISNUMBER(SEARCH("Fleet",RAW_INPUT!D5:D445)))*RAW_INPUT!F5:F445)/SUMPRODUCT((RAW_INPUT!A5:A445>=A32)*(RAW_INPUT!A5:A445<EDATE(A32,1))*(ISNUMBER(SEARCH("Fleet",RAW_INPUT!D5:D445)))*1),"-")} -> 3.845 | G100: =E32 -> 3.8134702 | H100: =IFERROR((G100-G99)/G99,"-") -> 0.076029932
A102: Max Price (Overall) | B102: =MAX(G80:G100) -> 3.840862
A103: Min Price (Overall) | B103: =MIN(G80:G100) -> 3.4524107
A104: Price Range | B104: =B102-B103 -> 0.38845135
A108: SEASONAL PATTERNS
A109: DAY OF WEEK ANALYSIS
A110: Day | B110: Revenue | C110: # Transactions | D110: Avg Sale | E110: % of Weekly Revenue
A111: Monday | B111: {=SUMPRODUCT((WEEKDAY(RAW_INPUT!A5:A445,1)=2)*RAW_INPUT!G5:G445)} -> 163108.25 | C111: {=SUMPRODUCT((WEEKDAY(RAW_INPUT!A5:A445,1)=2)*1)} -> 88 | D111: =IFERROR(B111/C111,0) -> 1853.5028 | E111: =B111/SUM(B111:B115) -> 0.20629377
A112: Tuesday | B112: {=SUMPRODUCT((WEEKDAY(RAW_INPUT!A5:A445,1)=3)*RAW_INPUT!G5:G445)} -> 171035.56 | C112: {=SUMPRODUCT((WEEKDAY(RAW_INPUT!A5:A445,1)=3)*1)} -> 90 | D112: =IFERROR(B112/C112,0) -> 1900.3951 | E112: =B112/SUM(B111:B115) -> 0.21631996
A113: Wednesday | B113: {=SUMPRODUCT((WEEKDAY(RAW_INPUT!A5:A445,1)=4)*RAW_INPUT!G5:G445)} -> 146387.14 | C113: {=SUMPRODUCT((WEEKDAY(RAW_INPUT!A5:A445,1)=4)*1)} -> 87 | D113: =IFERROR(B113/C113,0) -> 1682.6108 | E113: =B113/SUM(B111:B115) -> 0.18514548
A114: Thursday | B114: {=SUMPRODUCT((WEEKDAY(RAW_INPUT!A5:A445,1)=5)*RAW_INPUT!G5:G445)} -> 153388.14 | C114: {=SUMPRODUCT((WEEKDAY(RAW_INPUT!A5:A445,1)=5)*1)} -> 88 | D114: =IFERROR(B114/C114,0) -> 1743.047 | E114: =B114/SUM(B111:B115) -> 0.19400011
...
